nopolinfo #0
location: FailureLocation{className='com.facebook.presto.tests.TestTpchDistributedQueries', failingMethods=[com.facebook.presto.tests.TestTpchDistributedQueries#testNullOnLhsOfInPredicateAllowed, com.facebook.presto.tests.TestTpchDistributedQueries#testIntersect, com.facebook.presto.tests.TestTpchDistributedQueries#testUnion, com.facebook.presto.tests.TestTpchDistributedQueries#testExcept], erroringMethods=[], failures=[FailureType{failureName='java.lang.AssertionError', failureDetail='Execution of 'actual' query failed: SELECT NULL, NULL EXCEPT SELECT NULL, NULL FROM nation', isError=false}, FailureType{failureName='java.lang.AssertionError', failureDetail='Execution of 'actual' query failed: SELECT NULL, NULL INTERSECT SELECT NULL, NULL FROM nation', isError=false}, FailureType{failureName='java.lang.AssertionError', failureDetail='Execution of 'actual' query failed: SELECT NULL IN (SELECT NULL WHERE FALSE)', isError=false}, FailureType{failureName='java.lang.AssertionError', failureDetail='Execution of 'actual' query failed: SELECT NULL UNION SELECT NULL', isError=false}], nbFailures=4, nbErrors=0}
status: NOPATCH
dateEnd: Wed Mar 21 08:26:55 CET 2018
allocatedtime: 120minutes 
passingTime: 0minutes 
nb patches: 0
nopol context: Config{synthesisDepth=3, collectStaticMethods=true, collectStaticFields=false, collectLiterals=false, onlyOneSynthesisResult=false, sortExpressions=true, maxLineInvocationPerTest=250, timeoutMethodInvocation=2000, dataCollectionTimeoutInSecondForSynthesis=900, addWeight=0.19478, subWeight=0.04554, mulWeight=0.0102, divWeight=0.00613, andWeight=0.10597, orWeight=0.05708, eqWeight=0.22798, nEqWeight=0.0, lessEqWeight=0.0255, lessWeight=0.0947, methodCallWeight=0.1, fieldAccessWeight=0.08099, constantWeight=0.14232, variableWeight=0.05195, mode=REPAIR, type=COND_THEN_PRE, synthesis=DYNAMOTH, oracle=ANGELIC, solver=Z3, solverPath='./z3_for_linux', projectSources=[/root/workspace/prestodb/presto/356202150/presto-tests/src/main/java], projectClasspath='[Ljava.net.URL;@6272c96f', projectTests=[com.facebook.presto.tests.TestTpchDistributedQueries], complianceLevel=8, outputFolder=./workspace/prestodb/presto/356202150, json=false}
exception: null
nbStatements: 0
nbAngelicValues: 0
ignoreStatus: NOTHING_TO_IGNORE
----------



nopolinfo #1
location: FailureLocation{className='com.facebook.presto.tests.TestDistributedSpilledQueries', failingMethods=[com.facebook.presto.tests.TestDistributedSpilledQueries#testExcept, com.facebook.presto.tests.TestDistributedSpilledQueries#testNullOnLhsOfInPredicateAllowed, com.facebook.presto.tests.TestDistributedSpilledQueries#testIntersect, com.facebook.presto.tests.TestDistributedSpilledQueries#testUnion], erroringMethods=[], failures=[FailureType{failureName='java.lang.AssertionError', failureDetail='Execution of 'actual' query failed: SELECT NULL, NULL EXCEPT SELECT NULL, NULL FROM nation', isError=false}, FailureType{failureName='java.lang.AssertionError', failureDetail='Execution of 'actual' query failed: SELECT NULL, NULL INTERSECT SELECT NULL, NULL FROM nation', isError=false}, FailureType{failureName='java.lang.AssertionError', failureDetail='Execution of 'actual' query failed: SELECT NULL IN (SELECT NULL WHERE FALSE)', isError=false}, FailureType{failureName='java.lang.AssertionError', failureDetail='Execution of 'actual' query failed: SELECT NULL UNION SELECT NULL', isError=false}], nbFailures=4, nbErrors=0}
status: NOPATCH
dateEnd: Wed Mar 21 08:27:01 CET 2018
allocatedtime: 120minutes 
passingTime: 0minutes 
nb patches: 0
nopol context: Config{synthesisDepth=3, collectStaticMethods=true, collectStaticFields=false, collectLiterals=false, onlyOneSynthesisResult=false, sortExpressions=true, maxLineInvocationPerTest=250, timeoutMethodInvocation=2000, dataCollectionTimeoutInSecondForSynthesis=900, addWeight=0.19478, subWeight=0.04554, mulWeight=0.0102, divWeight=0.00613, andWeight=0.10597, orWeight=0.05708, eqWeight=0.22798, nEqWeight=0.0, lessEqWeight=0.0255, lessWeight=0.0947, methodCallWeight=0.1, fieldAccessWeight=0.08099, constantWeight=0.14232, variableWeight=0.05195, mode=REPAIR, type=COND_THEN_PRE, synthesis=DYNAMOTH, oracle=ANGELIC, solver=Z3, solverPath='./z3_for_linux', projectSources=[/root/workspace/prestodb/presto/356202150/presto-tests/src/main/java], projectClasspath='[Ljava.net.URL;@7198ab9a', projectTests=[com.facebook.presto.tests.TestDistributedSpilledQueries], complianceLevel=8, outputFolder=./workspace/prestodb/presto/356202150, json=false}
exception: null
nbStatements: 0
nbAngelicValues: 0
ignoreStatus: NOTHING_TO_IGNORE
----------



nopolinfo #2
location: FailureLocation{className='com.facebook.presto.memory.TestMemoryManager', failingMethods=[com.facebook.presto.memory.TestMemoryManager#testQueryMemoryLimit, com.facebook.presto.memory.TestMemoryManager#testQueryMemoryPerNodeLimit], erroringMethods=[], failures=[FailureType{failureName='com.facebook.presto.client.FailureInfo$FailureException', failureDetail='Error processing class definition:
// class version 52.0 (52)
// access flags 0x31
public final class com/facebook/presto/$gen/PagesHashStrategy_20180321_072335_14737 implements com/facebook/presto/operator/PagesHashStrategy  {


  // access flags 0x1A
  // signature J
  // declaration: long
  private final static J INSTANCE_SIZE

  // access flags 0x12
  // signature J
  // declaration: long
  private final J size

  // access flags 0x12
  // signature Ljava/util/List<Lcom/facebook/presto/spi/block/Block;>;
  // declaration: java.util.List<com.facebook.presto.spi.block.Block>
  private final Ljava/util/List; channel_0

  // access flags 0x12
  // signature Ljava/util/List<Lcom/facebook/presto/spi/block/Block;>;
  // declaration: java.util.List<com.facebook.presto.spi.block.Block>
  private final Ljava/util/List; channel_1

  // access flags 0x12
  // signature Ljava/util/List<Lcom/facebook/presto/spi/block/Block;>;
  // declaration: java.util.List<com.facebook.presto.spi.block.Block>
  private final Ljava/util/List; joinChannel_0

  // access flags 0x12
  // signature Ljava/util/List<Lcom/facebook/presto/spi/block/Block;>;
  // declaration: java.util.List<com.facebook.presto.spi.block.Block>
  private final Ljava/util/List; hashChannel

  // access flags 0x8
  // signature ()V
  // declaration: void <clinit>()
  static <clinit>()V
   L0
    LDC Lcom/facebook/presto/$gen/PagesHashStrategy_20180321_072335_14737;.class
    INVOKESTATIC org/openjdk/jol/info/ClassLayout.parseClass (Ljava/lang/Class;)Lorg/openjdk/jol/info/ClassLayout;
    INVOKEVIRTUAL org/openjdk/jol/info/ClassLayout.instanceSize ()I
    I2L
    PUTSTATIC com/facebook/presto/$gen/PagesHashStrategy_20180321_072335_14737.INSTANCE_SIZE : J
    RETURN
   L1
    MAXSTACK = -1
    MAXLOCALS = -1

  // access flags 0x1
  // signature (Ljava/util/List<Ljava/util/List<Lcom/facebook/presto/spi/block/Block;>;>;Ljava/util/OptionalInt;)V
  // declaration: void <init>(java.util.List<java.util.List<com.facebook.presto.spi.block.Block>>, java.util.OptionalInt)
  public <init>(Ljava/util/List;Ljava/util/OptionalInt;)V
   L0
    ALOAD 0
    INVOKESPECIAL java/lang/Object.<init> ()V
    ALOAD 0
    GETSTATIC com/facebook/presto/$gen/PagesHashStrategy_20180321_072335_14737.INSTANCE_SIZE : J
    PUTFIELD com/facebook/presto/$gen/PagesHashStrategy_20180321_072335_14737.size : J
    ALOAD 0
    ALOAD 1
    ICONST_0
    INVOKEINTERFACE java/util/List.get (I)Ljava/lang/Object;
    CHECKCAST java/util/List
    PUTFIELD com/facebook/presto/$gen/PagesHashStrategy_20180321_072335_14737.channel_0 : Ljava/util/List;
    ICONST_0
    ISTORE 3
   L1
    ILOAD 3
    ALOAD 1
    ICONST_0
    INVOKEINTERFACE java/util/List.get (I)Ljava/lang/Object;
    CHECKCAST java/util/List
    INVOKEINTERFACE java/util/List.size ()I
    INVOKESTATIC com/facebook/presto/sql/gen/CompilerOperations.lessThan (II)Z
    IFEQ L2
    ALOAD 0
    ALOAD 0
    GETFIELD com/facebook/presto/$gen/PagesHashStrategy_20180321_072335_14737.size : J
    ALOAD 1
    ICONST_0
    INVOKEINTERFACE java/util/List.get (I)Ljava/lang/Object;
    CHECKCAST java/util/List
    ILOAD 3
    INVOKEINTERFACE java/util/List.get (I)Ljava/lang/Object;
    CHECKCAST com/facebook/presto/spi/block/Block
    INVOKEINTERFACE com/facebook/presto/spi/block/Block.getRetainedSizeInBytes ()J
    LADD
    PUTFIELD com/facebook/presto/$gen/PagesHashStrategy_20180321_072335_14737.size : J
   L3
    IINC 3 1
    GOTO L1
   L2
    ALOAD 0
    ALOAD 1
    ICONST_1
    INVOKEINTERFACE java/util/List.get (I)Ljava/lang/Object;
    CHECKCAST java/util/List
    PUTFIELD com/facebook/presto/$gen/PagesHashStrategy_20180321_072335_14737.channel_1 : Ljava/util/List;
    ICONST_0
    ISTORE 3
   L4
    ILOAD 3
    ALOAD 1
    ICONST_1
    INVOKEINTERFACE java/util/List.get (I)Ljava/lang/Object;
    CHECKCAST java/util/List
    INVOKEINTERFACE java/util/List.size ()I
    INVOKESTATIC com/facebook/presto/sql/gen/CompilerOperations.lessThan (II)Z
    IFEQ L5
    ALOAD 0
    ALOAD 0
    GETFIELD com/facebook/presto/$gen/PagesHashStrategy_20180321_072335_14737.size : J
    ALOAD 1
    ICONST_1
    INVOKEINTERFACE java/util/List.get (I)Ljava/lang/Object;
    CHECKCAST java/util/List
    ILOAD 3
    INVOKEINTERFACE java/util/List.get (I)Ljava/lang/Object;
    CHECKCAST com/facebook/presto/spi/block/Block
    INVOKEINTERFACE com/facebook/presto/spi/block/Block.getRetainedSizeInBytes ()J
    LADD
    PUTFIELD com/facebook/presto/$gen/PagesHashStrategy_20180321_072335_14737.size : J
   L6
    IINC 3 1
    GOTO L4
   L5
    ALOAD 0
    ALOAD 1
    ICONST_0
    INVOKEINTERFACE java/util/List.get (I)Ljava/lang/Object;
    CHECKCAST java/util/List
    PUTFIELD com/facebook/presto/$gen/PagesHashStrategy_20180321_072335_14737.joinChannel_0 : Ljava/util/List;
    ALOAD 2
    INVOKEVIRTUAL java/util/OptionalInt.isPresent ()Z
    IFEQ L7
    ALOAD 0
    ALOAD 1
    ALOAD 2
    INVOKEVIRTUAL java/util/OptionalInt.getAsInt ()I
    INVOKEINTERFACE java/util/List.get (I)Ljava/lang/Object;
    PUTFIELD com/facebook/presto/$gen/PagesHashStrategy_20180321_072335_14737.hashChannel : Ljava/util/List;
    GOTO L8
   L7
    ALOAD 0
    ACONST_NULL
    PUTFIELD com/facebook/presto/$gen/PagesHashStrategy_20180321_072335_14737.hashChannel : Ljava/util/List;
   L8
    RETURN
   L9
    LOCALVARIABLE this Lcom/facebook/presto/$gen/PagesHashStrategy_20180321_072335_14737; L0 L9 0
    // signature Lcom/facebook/presto/$gen/PagesHashStrategy_20180321_072335_14737;
    // declaration: com.facebook.presto.$gen.PagesHashStrategy_20180321_072335_14737
    LOCALVARIABLE channels Ljava/util/List; L0 L9 1
    // signature Ljava/util/List<Ljava/util/List<Lcom/facebook/presto/spi/block/Block;>;>;
    // declaration: java.util.List<java.util.List<com.facebook.presto.spi.block.Block>>
    LOCALVARIABLE hashChannel Ljava/util/OptionalInt; L0 L9 2
    // signature Ljava/util/OptionalInt;
    // declaration: java.util.OptionalInt
    LOCALVARIABLE blockIndex I L0 L9 3
    // signature I
    // declaration: int
    MAXSTACK = -1
    MAXLOCALS = -1

  // access flags 0x1
  // signature ()I
  // declaration: int getChannelCount()
  public getChannelCount()I
   L0
    ICONST_2
    IRETURN
   L1
    LOCALVARIABLE this Lcom/facebook/presto/$gen/PagesHashStrategy_20180321_072335_14737; L0 L1 0
    // signature Lcom/facebook/presto/$gen/PagesHashStrategy_20180321_072335_14737;
    // declaration: com.facebook.presto.$gen.PagesHashStrategy_20180321_072335_14737
    MAXSTACK = -1
    MAXLOCALS = -1

  // access flags 0x1
  // signature ()J
  // declaration: long getSizeInBytes()
  public getSizeInBytes()J
   L0
    ALOAD 0
    GETFIELD com/facebook/presto/$gen/PagesHashStrategy_20180321_072335_14737.size : J
    LRETURN
   L1
    LOCALVARIABLE this Lcom/facebook/presto/$gen/PagesHashStrategy_20180321_072335_14737; L0 L1 0
    // signature Lcom/facebook/presto/$gen/PagesHashStrategy_20180321_072335_14737;
    // declaration: com.facebook.presto.$gen.PagesHashStrategy_20180321_072335_14737
    MAXSTACK = -1
    MAXLOCALS = -1

  // access flags 0x1
  // signature (IILcom/facebook/presto/spi/PageBuilder;I)V
  // declaration: void appendTo(int, int, com.facebook.presto.spi.PageBuilder, int)
  public appendTo(IILcom/facebook/presto/spi/PageBuilder;I)V
   L0
    INVOKEDYNAMIC array_varchar_1_()Lcom/facebook/presto/spi/type/Type; [
      // handle kind 0x6 : INVOKESTATIC
      com/facebook/presto/sql/gen/Bootstrap.bootstrap(Ljava/lang/invoke/MethodHandles$Lookup;Ljava/lang/String;Ljava/lang/invoke/MethodType;J)Ljava/lang/invoke/CallSite;
      // arguments:
      0
    ]
    ALOAD 0
    GETFIELD com/facebook/presto/$gen/PagesHashStrategy_20180321_072335_14737.channel_0 : Ljava/util/List;
    ILOAD 1
    INVOKEINTERFACE java/util/List.get (I)Ljava/lang/Object;
    CHECKCAST com/facebook/presto/spi/block/Block
    ILOAD 2
    ALOAD 3
    ILOAD 4
    ICONST_0
    IADD
    INVOKEVIRTUAL com/facebook/presto/spi/PageBuilder.getBlockBuilder (I)Lcom/facebook/presto/spi/block/BlockBuilder;
    INVOKEINTERFACE com/facebook/presto/spi/type/Type.appendTo (Lcom/facebook/presto/spi/block/Block;ILcom/facebook/presto/spi/block/BlockBuilder;)V
    INVOKEDYNAMIC bigint()Lcom/facebook/presto/spi/type/Type; [
      // handle kind 0x6 : INVOKESTATIC
      com/facebook/presto/sql/gen/Bootstrap.bootstrap(Ljava/lang/invoke/MethodHandles$Lookup;Ljava/lang/String;Ljava/lang/invoke/MethodType;J)Ljava/lang/invoke/CallSite;
      // arguments:
      1
    ]
    ALOAD 0
    GETFIELD com/facebook/presto/$gen/PagesHashStrategy_20180321_072335_14737.channel_1 : Ljava/util/List;
    ILOAD 1
    INVOKEINTERFACE java/util/List.get (I)Ljava/lang/Object;
    CHECKCAST com/facebook/presto/spi/block/Block
    ILOAD 2
    ALOAD 3
    ILOAD 4
    ICONST_1
    IADD
    INVOKEVIRTUAL com/facebook/presto/spi/PageBuilder.getBlockBuilder (I)Lcom/facebook/presto/spi/block/BlockBuilder;
    INVOKEINTERFACE com/facebook/presto/spi/type/Type.appendTo (Lcom/facebook/presto/spi/block/Block;ILcom/facebook/presto/spi/block/BlockBuilder;)V
    RETURN
   L1
    LOCALVARIABLE this Lcom/facebook/presto/$gen/PagesHashStrategy_20180321_072335_14737; L0 L1 0
    // signature Lcom/facebook/presto/$gen/PagesHashStrategy_20180321_072335_14737;
    // declaration: com.facebook.presto.$gen.PagesHashStrategy_20180321_072335_14737
    LOCALVARIABLE blockIndex I L0 L1 1
    // signature I
    // declaration: int
    LOCALVARIABLE blockPosition I L0 L1 2
    // signature I
    // declaration: int
    LOCALVARIABLE pageBuilder Lcom/facebook/presto/spi/PageBuilder; L0 L1 3
    // signature Lcom/facebook/presto/spi/PageBuilder;
    // declaration: com.facebook.presto.spi.PageBuilder
    LOCALVARIABLE outputChannelOffset I L0 L1 4
    // signature I
    // declaration: int
    MAXSTACK = -1
    MAXLOCALS = -1

  // access flags 0x1
  // signature (II)J
  // declaration: long hashPosition(int, int)
  public hashPosition(II)J
   L0
    ALOAD 0
    GETFIELD com/facebook/presto/$gen/PagesHashStrategy_20180321_072335_14737.hashChannel : Ljava/util/List;
    ACONST_NULL
    IF_ACMPEQ L1
    ICONST_1
    GOTO L2
   L1
    ICONST_0
   L2
    IFEQ L3
    INVOKEDYNAMIC bigint()Lcom/facebook/presto/spi/type/Type; [
      // handle kind 0x6 : INVOKESTATIC
      com/facebook/presto/sql/gen/Bootstrap.bootstrap(Ljava/lang/invoke/MethodHandles$Lookup;Ljava/lang/String;Ljava/lang/invoke/MethodType;J)Ljava/lang/invoke/CallSite;
      // arguments:
      2
    ]
    ALOAD 0
    GETFIELD com/facebook/presto/$gen/PagesHashStrategy_20180321_072335_14737.hashChannel : Ljava/util/List;
    ILOAD 1
    INVOKEINTERFACE java/util/List.get (I)Ljava/lang/Object;
    CHECKCAST com/facebook/presto/spi/block/Block
    ILOAD 2
    INVOKEINTERFACE com/facebook/presto/spi/type/Type.getLong (Lcom/facebook/presto/spi/block/Block;I)J
    LRETURN
   L3
    LCONST_0
    LSTORE 3
    LLOAD 3
    LDC 31
    LMUL
    ALOAD 0
    GETFIELD com/facebook/presto/$gen/PagesHashStrategy_20180321_072335_14737.joinChannel_0 : Ljava/util/List;
    ILOAD 1
    INVOKEINTERFACE java/util/List.get (I)Ljava/lang/Object;
    CHECKCAST com/facebook/presto/spi/block/Block
    ILOAD 2
    INVOKEINTERFACE com/facebook/presto/spi/block/Block.isNull (I)Z
    IFEQ L4
    LCONST_0
    GOTO L5
   L4
    INVOKEDYNAMIC array_varchar_1_()Lcom/facebook/presto/spi/type/Type; [
      // handle kind 0x6 : INVOKESTATIC
      com/facebook/presto/sql/gen/Bootstrap.bootstrap(Ljava/lang/invoke/MethodHandles$Lookup;Ljava/lang/String;Ljava/lang/invoke/MethodType;J)Ljava/lang/invoke/CallSite;
      // arguments:
      3
    ]
    ALOAD 0
    GETFIELD com/facebook/presto/$gen/PagesHashStrategy_20180321_072335_14737.joinChannel_0 : Ljava/util/List;
    ILOAD 1
    INVOKEINTERFACE java/util/List.get (I)Ljava/lang/Object;
    CHECKCAST com/facebook/presto/spi/block/Block
    ILOAD 2
    INVOKEINTERFACE com/facebook/presto/spi/type/Type.hash (Lcom/facebook/presto/spi/block/Block;I)J
   L5
    LADD
    LSTORE 3
    LLOAD 3
    LRETURN
   L6
    LOCALVARIABLE this Lcom/facebook/presto/$gen/PagesHashStrategy_20180321_072335_14737; L0 L6 0
    // signature Lcom/facebook/presto/$gen/PagesHashStrategy_20180321_072335_14737;
    // declaration: com.facebook.presto.$gen.PagesHashStrategy_20180321_072335_14737
    LOCALVARIABLE blockIndex I L0 L6 1
    // signature I
    // declaration: int
    LOCALVARIABLE blockPosition I L0 L6 2
    // signature I
    // declaration: int
    LOCALVARIABLE result J L0 L6 3
    // signature J
    // declaration: long
    MAXSTACK = -1
    MAXLOCALS = -1

  // access flags 0x1
  // signature (ILcom/facebook/presto/spi/Page;)J
  // declaration: long hashRow(int, com.facebook.presto.spi.Page)
  public hashRow(ILcom/facebook/presto/spi/Page;)J
   L0
    LCONST_0
    LSTORE 3
    LLOAD 3
    LDC 31
    LMUL
    ALOAD 2
    ICONST_0
    INVOKEVIRTUAL com/facebook/presto/spi/Page.getBlock (I)Lcom/facebook/presto/spi/block/Block;
    ILOAD 1
    INVOKEINTERFACE com/facebook/presto/spi/block/Block.isNull (I)Z
    IFEQ L1
    LCONST_0
    GOTO L2
   L1
    INVOKEDYNAMIC array_varchar_1_()Lcom/facebook/presto/spi/type/Type; [
      // handle kind 0x6 : INVOKESTATIC
      com/facebook/presto/sql/gen/Bootstrap.bootstrap(Ljava/lang/invoke/MethodHandles$Lookup;Ljava/lang/String;Ljava/lang/invoke/MethodType;J)Ljava/lang/invoke/CallSite;
      // arguments:
      4
    ]
    ALOAD 2
    ICONST_0
    INVOKEVIRTUAL com/facebook/presto/spi/Page.getBlock (I)Lcom/facebook/presto/spi/block/Block;
    ILOAD 1
    INVOKEINTERFACE com/facebook/presto/spi/type/Type.hash (Lcom/facebook/presto/spi/block/Block;I)J
   L2
    LADD
    LSTORE 3
    LLOAD 3
    LRETURN
   L3
    LOCALVARIABLE this Lcom/facebook/presto/$gen/PagesHashStrategy_20180321_072335_14737; L0 L3 0
    // signature Lcom/facebook/presto/$gen/PagesHashStrategy_20180321_072335_14737;
    // declaration: com.facebook.presto.$gen.PagesHashStrategy_20180321_072335_14737
    LOCALVARIABLE position I L0 L3 1
    // signature I
    // declaration: int
    LOCALVARIABLE blocks Lcom/facebook/presto/spi/Page; L0 L3 2
    // signature Lcom/facebook/presto/spi/Page;
    // declaration: com.facebook.presto.spi.Page
    LOCALVARIABLE result J L0 L3 3
    // signature J
    // declaration: long
    MAXSTACK = -1
    MAXLOCALS = -1

  // access flags 0x1
  // signature (ILcom/facebook/presto/spi/Page;ILcom/facebook/presto/spi/Page;)Z
  // declaration: boolean rowEqualsRow(int, com.facebook.presto.spi.Page, int, com.facebook.presto.spi.Page)
  public rowEqualsRow(ILcom/facebook/presto/spi/Page;ILcom/facebook/presto/spi/Page;)Z
   L0
    ALOAD 2
    ICONST_0
    INVOKEVIRTUAL com/facebook/presto/spi/Page.getBlock (I)Lcom/facebook/presto/spi/block/Block;
    ILOAD 1
    INVOKEINTERFACE com/facebook/presto/spi/block/Block.isNull (I)Z
    ALOAD 4
    ICONST_0
    INVOKEVIRTUAL com/facebook/presto/spi/Page.getBlock (I)Lcom/facebook/presto/spi/block/Block;
    ILOAD 3
    INVOKEINTERFACE com/facebook/presto/spi/block/Block.isNull (I)Z
    IOR
    IFEQ L1
    ALOAD 2
    ICONST_0
    INVOKEVIRTUAL com/facebook/presto/spi/Page.getBlock (I)Lcom/facebook/presto/spi/block/Block;
    ILOAD 1
    INVOKEINTERFACE com/facebook/presto/spi/block/Block.isNull (I)Z
    ALOAD 4
    ICONST_0
    INVOKEVIRTUAL com/facebook/presto/spi/Page.getBlock (I)Lcom/facebook/presto/spi/block/Block;
    ILOAD 3
    INVOKEINTERFACE com/facebook/presto/spi/block/Block.isNull (I)Z
    IAND
    GOTO L2
   L1
    INVOKEDYNAMIC array_varchar_1_()Lcom/facebook/presto/spi/type/Type; [
      // handle kind 0x6 : INVOKESTATIC
      com/facebook/presto/sql/gen/Bootstrap.bootstrap(Ljava/lang/invoke/MethodHandles$Lookup;Ljava/lang/String;Ljava/lang/invoke/MethodType;J)Ljava/lang/invoke/CallSite;
      // arguments:
      5
    ]
    ALOAD 2
    ICONST_0
    INVOKEVIRTUAL com/facebook/presto/spi/Page.getBlock (I)Lcom/facebook/presto/spi/block/Block;
    ILOAD 1
    ALOAD 4
    ICONST_0
    INVOKEVIRTUAL com/facebook/presto/spi/Page.getBlock (I)Lcom/facebook/presto/spi/block/Block;
    ILOAD 3
    INVOKEINTERFACE com/facebook/presto/spi/type/Type.equalTo (Lcom/facebook/presto/spi/block/Block;ILcom/facebook/presto/spi/block/Block;I)Z
   L2
    IFNE L3
    ICONST_0
    IRETURN
   L3
    ICONST_1
    IRETURN
   L4
    LOCALVARIABLE this Lcom/facebook/presto/$gen/PagesHashStrategy_20180321_072335_14737; L0 L4 0
    // signature Lcom/facebook/presto/$gen/PagesHashStrategy_20180321_072335_14737;
    // declaration: com.facebook.presto.$gen.PagesHashStrategy_20180321_072335_14737
    LOCALVARIABLE leftPosition I L0 L4 1
    // signature I
    // declaration: int
    LOCALVARIABLE leftPage Lcom/facebook/presto/spi/Page; L0 L4 2
    // signature Lcom/facebook/presto/spi/Page;
    // declaration: com.facebook.presto.spi.Page
    LOCALVARIABLE rightPosition I L0 L4 3
    // signature I
    // declaration: int
    LOCALVARIABLE rightPage Lcom/facebook/presto/spi/Page; L0 L4 4
    // signature Lcom/facebook/presto/spi/Page;
    // declaration: com.facebook.presto.spi.Page
    MAXSTACK = -1
    MAXLOCALS = -1

  // access flags 0x1
  // signature (IIILcom/facebook/presto/spi/Page;)Z
  // declaration: boolean positionEqualsRowIgnoreNulls(int, int, int, com.facebook.presto.spi.Page)
  public positionEqualsRowIgnoreNulls(IIILcom/facebook/presto/spi/Page;)Z
   L0
    INVOKEDYNAMIC array_varchar_1_()Lcom/facebook/presto/spi/type/Type; [
      // handle kind 0x6 : INVOKESTATIC
      com/facebook/presto/sql/gen/Bootstrap.bootstrap(Ljava/lang/invoke/MethodHandles$Lookup;Ljava/lang/String;Ljava/lang/invoke/MethodType;J)Ljava/lang/invoke/CallSite;
      // arguments:
      6
    ]
    ALOAD 0
    GETFIELD com/facebook/presto/$gen/PagesHashStrategy_20180321_072335_14737.joinChannel_0 : Ljava/util/List;
    ILOAD 1
    INVOKEINTERFACE java/util/List.get (I)Ljava/lang/Object;
    CHECKCAST com/facebook/presto/spi/block/Block
    ILOAD 2
    ALOAD 4
    ICONST_0
    INVOKEVIRTUAL com/facebook/presto/spi/Page.getBlock (I)Lcom/facebook/presto/spi/block/Block;
    ILOAD 3
    INVOKEINTERFACE com/facebook/presto/spi/type/Type.equalTo (Lcom/facebook/presto/spi/block/Block;ILcom/facebook/presto/spi/block/Block;I)Z
    IFNE L1
    ICONST_0
    IRETURN
   L1
    ICONST_1
    IRETURN
   L2
    LOCALVARIABLE this Lcom/facebook/presto/$gen/PagesHashStrategy_20180321_072335_14737; L0 L2 0
    // signature Lcom/facebook/presto/$gen/PagesHashStrategy_20180321_072335_14737;
    // declaration: com.facebook.presto.$gen.PagesHashStrategy_20180321_072335_14737
    LOCALVARIABLE leftBlockIndex I L0 L2 1
    // signature I
    // declaration: int
    LOCALVARIABLE leftBlockPosition I L0 L2 2
    // signature I
    // declaration: int
    LOCALVARIABLE rightPosition I L0 L2 3
    // signature I
    // declaration: int
    LOCALVARIABLE rightPage Lcom/facebook/presto/spi/Page; L0 L2 4
    // signature Lcom/facebook/presto/spi/Page;
    // declaration: com.facebook.presto.spi.Page
    MAXSTACK = -1
    MAXLOCALS = -1

  // access flags 0x1
  // signature (IIILcom/facebook/presto/spi/Page;)Z
  // declaration: boolean positionEqualsRow(int, int, int, com.facebook.presto.spi.Page)
  public positionEqualsRow(IIILcom/facebook/presto/spi/Page;)Z
   L0
    ALOAD 0
    GETFIELD com/facebook/presto/$gen/PagesHashStrategy_20180321_072335_14737.joinChannel_0 : Ljava/util/List;
    ILOAD 1
    INVOKEINTERFACE java/util/List.get (I)Ljava/lang/Object;
    CHECKCAST com/facebook/presto/spi/block/Block
    ILOAD 2
    INVOKEINTERFACE com/facebook/presto/spi/block/Block.isNull (I)Z
    ALOAD 4
    ICONST_0
    INVOKEVIRTUAL com/facebook/presto/spi/Page.getBlock (I)Lcom/facebook/presto/spi/block/Block;
    ILOAD 3
    INVOKEINTERFACE com/facebook/presto/spi/block/Block.isNull (I)Z
    IOR
    IFEQ L1
    ALOAD 0
    GETFIELD com/facebook/presto/$gen/PagesHashStrategy_20180321_072335_14737.joinChannel_0 : Ljava/util/List;
    ILOAD 1
    INVOKEINTERFACE java/util/List.get (I)Ljava/lang/Object;
    CHECKCAST com/facebook/presto/spi/block/Block
    ILOAD 2
    INVOKEINTERFACE com/facebook/presto/spi/block/Block.isNull (I)Z
    ALOAD 4
    ICONST_0
    INVOKEVIRTUAL com/facebook/presto/spi/Page.getBlock (I)Lcom/facebook/presto/spi/block/Block;
    ILOAD 3
    INVOKEINTERFACE com/facebook/presto/spi/block/Block.isNull (I)Z
    IAND
    GOTO L2
   L1
    INVOKEDYNAMIC array_varchar_1_()Lcom/facebook/presto/spi/type/Type; [
      // handle kind 0x6 : INVOKESTATIC
      com/facebook/presto/sql/gen/Bootstrap.bootstrap(Ljava/lang/invoke/MethodHandles$Lookup;Ljava/lang/String;Ljava/lang/invoke/MethodType;J)Ljava/lang/invoke/CallSite;
      // arguments:
      7
    ]
    ALOAD 0
    GETFIELD com/facebook/presto/$gen/PagesHashStrategy_20180321_072335_14737.joinChannel_0 : Ljava/util/List;
    ILOAD 1
    INVOKEINTERFACE java/util/List.get (I)Ljava/lang/Object;
    CHECKCAST com/facebook/presto/spi/block/Block
    ILOAD 2
    ALOAD 4
    ICONST_0
    INVOKEVIRTUAL com/facebook/presto/spi/Page.getBlock (I)Lcom/facebook/presto/spi/block/Block;
    ILOAD 3
    INVOKEINTERFACE com/facebook/presto/spi/type/Type.equalTo (Lcom/facebook/presto/spi/block/Block;ILcom/facebook/presto/spi/block/Block;I)Z
   L2
    IFNE L3
    ICONST_0
    IRETURN
   L3
    ICONST_1
    IRETURN
   L4
    LOCALVARIABLE this Lcom/facebook/presto/$gen/PagesHashStrategy_20180321_072335_14737; L0 L4 0
    // signature Lcom/facebook/presto/$gen/PagesHashStrategy_20180321_072335_14737;
    // declaration: com.facebook.presto.$gen.PagesHashStrategy_20180321_072335_14737
    LOCALVARIABLE leftBlockIndex I L0 L4 1
    // signature I
    // declaration: int
    LOCALVARIABLE leftBlockPosition I L0 L4 2
    // signature I
    // declaration: int
    LOCALVARIABLE rightPosition I L0 L4 3
    // signature I
    // declaration: int
    LOCALVARIABLE rightPage Lcom/facebook/presto/spi/Page; L0 L4 4
    // signature Lcom/facebook/presto/spi/Page;
    // declaration: com.facebook.presto.spi.Page
    MAXSTACK = -1
    MAXLOCALS = -1

  // access flags 0x1
  // signature (IIILcom/facebook/presto/spi/Page;[I)Z
  // declaration: boolean positionEqualsRow(int, int, int, com.facebook.presto.spi.Page, int[])
  public positionEqualsRow(IIILcom/facebook/presto/spi/Page;[I)Z
   L0
    INVOKEDYNAMIC array_varchar_1_()Lcom/facebook/presto/spi/type/Type; [
      // handle kind 0x6 : INVOKESTATIC
      com/facebook/presto/sql/gen/Bootstrap.bootstrap(Ljava/lang/invoke/MethodHandles$Lookup;Ljava/lang/String;Ljava/lang/invoke/MethodType;J)Ljava/lang/invoke/CallSite;
      // arguments:
      8
    ]
    ALOAD 0
    GETFIELD com/facebook/presto/$gen/PagesHashStrategy_20180321_072335_14737.joinChannel_0 : Ljava/util/List;
    ILOAD 1
    INVOKEINTERFACE java/util/List.get (I)Ljava/lang/Object;
    CHECKCAST com/facebook/presto/spi/block/Block
    ILOAD 2
    INVOKEINTERFACE com/facebook/presto/spi/type/Type.getObject (Lcom/facebook/presto/spi/block/Block;I)Ljava/lang/Object;
    CHECKCAST com/facebook/presto/spi/block/Block
    INVOKEDYNAMIC array_varchar_1_()Lcom/facebook/presto/spi/type/Type; [
      // handle kind 0x6 : INVOKESTATIC
      com/facebook/presto/sql/gen/Bootstrap.bootstrap(Ljava/lang/invoke/MethodHandles$Lookup;Ljava/lang/String;Ljava/lang/invoke/MethodType;J)Ljava/lang/invoke/CallSite;
      // arguments:
      8
    ]
    ALOAD 4
    ALOAD 5
    ICONST_0
    IALOAD
    INVOKEVIRTUAL com/facebook/presto/spi/Page.getBlock (I)Lcom/facebook/presto/spi/block/Block;
    ILOAD 3
    INVOKEINTERFACE com/facebook/presto/spi/type/Type.getObject (Lcom/facebook/presto/spi/block/Block;I)Ljava/lang/Object;
    CHECKCAST com/facebook/presto/spi/block/Block
    INVOKEDYNAMIC $operator$IS_DISTINCT_FROM(Lcom/facebook/presto/spi/block/Block;ZLcom/facebook/presto/spi/block/Block;Z)Z [
      // handle kind 0x6 : INVOKESTATIC
      com/facebook/presto/sql/gen/Bootstrap.bootstrap(Ljava/lang/invoke/MethodHandles$Lookup;Ljava/lang/String;Ljava/lang/invoke/MethodType;J)Ljava/lang/invoke/CallSite;
      // arguments:
      9
    ]
   L1
    IFEQ L2
    ICONST_0
    IRETURN
   L2
    ICONST_1
    IRETURN
   L3
    LOCALVARIABLE this Lcom/facebook/presto/$gen/PagesHashStrategy_20180321_072335_14737; L0 L3 0
    // signature Lcom/facebook/presto/$gen/PagesHashStrategy_20180321_072335_14737;
    // declaration: com.facebook.presto.$gen.PagesHashStrategy_20180321_072335_14737
    LOCALVARIABLE leftBlockIndex I L0 L3 1
    // signature I
    // declaration: int
    LOCALVARIABLE leftBlockPosition I L0 L3 2
    // signature I
    // declaration: int
    LOCALVARIABLE rightPosition I L0 L3 3
    // signature I
    // declaration: int
    LOCALVARIABLE page Lcom/facebook/presto/spi/Page; L0 L3 4
    // signature Lcom/facebook/presto/spi/Page;
    // declaration: com.facebook.presto.spi.Page
    LOCALVARIABLE rightChannels [I L0 L3 5
    // signature [I
    // declaration: int[]
    MAXSTACK = -1
    MAXLOCALS = -1

  // access flags 0x1
  // signature (IIII)Z
  // declaration: boolean positionEqualsPositionIgnoreNulls(int, int, int, int)
  public positionEqualsPositionIgnoreNulls(IIII)Z
   L0
    INVOKEDYNAMIC array_varchar_1_()Lcom/facebook/presto/spi/type/Type; [
      // handle kind 0x6 : INVOKESTATIC
      com/facebook/presto/sql/gen/Bootstrap.bootstrap(Ljava/lang/invoke/MethodHandles$Lookup;Ljava/lang/String;Ljava/lang/invoke/MethodType;J)Ljava/lang/invoke/CallSite;
      // arguments:
      10
    ]
    ALOAD 0
    GETFIELD com/facebook/presto/$gen/PagesHashStrategy_20180321_072335_14737.joinChannel_0 : Ljava/util/List;
    ILOAD 1
    INVOKEINTERFACE java/util/List.get (I)Ljava/lang/Object;
    CHECKCAST com/facebook/presto/spi/block/Block
    ILOAD 2
    ALOAD 0
    GETFIELD com/facebook/presto/$gen/PagesHashStrategy_20180321_072335_14737.joinChannel_0 : Ljava/util/List;
    ILOAD 3
    INVOKEINTERFACE java/util/List.get (I)Ljava/lang/Object;
    CHECKCAST com/facebook/presto/spi/block/Block
    ILOAD 4
    INVOKEINTERFACE com/facebook/presto/spi/type/Type.equalTo (Lcom/facebook/presto/spi/block/Block;ILcom/facebook/presto/spi/block/Block;I)Z
    IFNE L1
    ICONST_0
    IRETURN
   L1
    ICONST_1
    IRETURN
   L2
    LOCALVARIABLE this Lcom/facebook/presto/$gen/PagesHashStrategy_20180321_072335_14737; L0 L2 0
    // signature Lcom/facebook/presto/$gen/PagesHashStrategy_20180321_072335_14737;
    // declaration: com.facebook.presto.$gen.PagesHashStrategy_20180321_072335_14737
    LOCALVARIABLE leftBlockIndex I L0 L2 1
    // signature I
    // declaration: int
    LOCALVARIABLE leftBlockPosition I L0 L2 2
    // signature I
    // declaration: int
    LOCALVARIABLE rightBlockIndex I L0 L2 3
    // signature I
    // declaration: int
    LOCALVARIABLE rightBlockPosition I L0 L2 4
    // signature I
    // declaration: int
    MAXSTACK = -1
    MAXLOCALS = -1

  // access flags 0x1
  // signature (IIII)Z
  // declaration: boolean positionEqualsPosition(int, int, int, int)
  public positionEqualsPosition(IIII)Z
   L0
    ALOAD 0
    GETFIELD com/facebook/presto/$gen/PagesHashStrategy_20180321_072335_14737.joinChannel_0 : Ljava/util/List;
    ILOAD 1
    INVOKEINTERFACE java/util/List.get (I)Ljava/lang/Object;
    CHECKCAST com/facebook/presto/spi/block/Block
    ILOAD 2
    INVOKEINTERFACE com/facebook/presto/spi/block/Block.isNull (I)Z
    ALOAD 0
    GETFIELD com/facebook/presto/$gen/PagesHashStrategy_20180321_072335_14737.joinChannel_0 : Ljava/util/List;
    ILOAD 3
    INVOKEINTERFACE java/util/List.get (I)Ljava/lang/Object;
    CHECKCAST com/facebook/presto/spi/block/Block
    ILOAD 4
    INVOKEINTERFACE com/facebook/presto/spi/block/Block.isNull (I)Z
    IOR
    IFEQ L1
    ALOAD 0
    GETFIELD com/facebook/presto/$gen/PagesHashStrategy_20180321_072335_14737.joinChannel_0 : Ljava/util/List;
    ILOAD 1
    INVOKEINTERFACE java/util/List.get (I)Ljava/lang/Object;
    CHECKCAST com/facebook/presto/spi/block/Block
    ILOAD 2
    INVOKEINTERFACE com/facebook/presto/spi/block/Block.isNull (I)Z
    ALOAD 0
    GETFIELD com/facebook/presto/$gen/PagesHashStrategy_20180321_072335_14737.joinChannel_0 : Ljava/util/List;
    ILOAD 3
    INVOKEINTERFACE java/util/List.get (I)Ljava/lang/Object;
    CHECKCAST com/facebook/presto/spi/block/Block
    ILOAD 4
    INVOKEINTERFACE com/facebook/presto/spi/block/Block.isNull (I)Z
    IAND
    GOTO L2
   L1
    INVOKEDYNAMIC array_varchar_1_()Lcom/facebook/presto/spi/type/Type; [
      // handle kind 0x6 : INVOKESTATIC
      com/facebook/presto/sql/gen/Bootstrap.bootstrap(Ljava/lang/invoke/MethodHandles$Lookup;Ljava/lang/String;Ljava/lang/invoke/MethodType;J)Ljava/lang/invoke/CallSite;
      // arguments:
      11
    ]
    ALOAD 0
    GETFIELD com/facebook/presto/$gen/PagesHashStrategy_20180321_072335_14737.joinChannel_0 : Ljava/util/List;
    ILOAD 1
    INVOKEINTERFACE java/util/List.get (I)Ljava/lang/Object;
    CHECKCAST com/facebook/presto/spi/block/Block
    ILOAD 2
    ALOAD 0
    GETFIELD com/facebook/presto/$gen/PagesHashStrategy_20180321_072335_14737.joinChannel_0 : Ljava/util/List;
    ILOAD 3
    INVOKEINTERFACE java/util/List.get (I)Ljava/lang/Object;
    CHECKCAST com/facebook/presto/spi/block/Block
    ILOAD 4
    INVOKEINTERFACE com/facebook/presto/spi/type/Type.equalTo (Lcom/facebook/presto/spi/block/Block;ILcom/facebook/presto/spi/block/Block;I)Z
   L2
    IFNE L3
    ICONST_0
    IRETURN
   L3
    ICONST_1
    IRETURN
   L4
    LOCALVARIABLE this Lcom/facebook/presto/$gen/PagesHashStrategy_20180321_072335_14737; L0 L4 0
    // signature Lcom/facebook/presto/$gen/PagesHashStrategy_20180321_072335_14737;
    // declaration: com.facebook.presto.$gen.PagesHashStrategy_20180321_072335_14737
    LOCALVARIABLE leftBlockIndex I L0 L4 1
    // signature I
    // declaration: int
    LOCALVARIABLE leftBlockPosition I L0 L4 2
    // signature I
    // declaration: int
    LOCALVARIABLE rightBlockIndex I L0 L4 3
    // signature I
    // declaration: int
    LOCALVARIABLE rightBlockPosition I L0 L4 4
    // signature I
    // declaration: int
    MAXSTACK = -1
    MAXLOCALS = -1

  // access flags 0x1
  // signature (II)Z
  // declaration: boolean isPositionNull(int, int)
  public isPositionNull(II)Z
   L0
    ALOAD 0
    GETFIELD com/facebook/presto/$gen/PagesHashStrategy_20180321_072335_14737.joinChannel_0 : Ljava/util/List;
    ILOAD 1
    INVOKEINTERFACE java/util/List.get (I)Ljava/lang/Object;
    CHECKCAST com/facebook/presto/spi/block/Block
    ILOAD 2
    INVOKEINTERFACE com/facebook/presto/spi/block/Block.isNull (I)Z
    IFEQ L1
    ICONST_1
    IRETURN
   L1
    ICONST_0
    IRETURN
   L2
    LOCALVARIABLE this Lcom/facebook/presto/$gen/PagesHashStrategy_20180321_072335_14737; L0 L2 0
    // signature Lcom/facebook/presto/$gen/PagesHashStrategy_20180321_072335_14737;
    // declaration: com.facebook.presto.$gen.PagesHashStrategy_20180321_072335_14737
    LOCALVARIABLE blockIndex I L0 L2 1
    // signature I
    // declaration: int
    LOCALVARIABLE blockPosition I L0 L2 2
    // signature I
    // declaration: int
    MAXSTACK = -1
    MAXLOCALS = -1

  // access flags 0x1
  // signature (IIII)I
  // declaration: int compareSortChannelPositions(int, int, int, int)
  public compareSortChannelPositions(IIII)I
   L0
    NEW java/lang/UnsupportedOperationException
    DUP
    INVOKESPECIAL java/lang/UnsupportedOperationException.<init> ()V
    ATHROW
   L1
    LOCALVARIABLE this Lcom/facebook/presto/$gen/PagesHashStrategy_20180321_072335_14737; L0 L1 0
    // signature Lcom/facebook/presto/$gen/PagesHashStrategy_20180321_072335_14737;
    // declaration: com.facebook.presto.$gen.PagesHashStrategy_20180321_072335_14737
    LOCALVARIABLE leftBlockIndex I L0 L1 1
    // signature I
    // declaration: int
    LOCALVARIABLE leftBlockPosition I L0 L1 2
    // signature I
    // declaration: int
    LOCALVARIABLE rightBlockIndex I L0 L1 3
    // signature I
    // declaration: int
    LOCALVARIABLE rightBlockPosition I L0 L1 4
    // signature I
    // declaration: int
    MAXSTACK = -1
    MAXLOCALS = -1

  // access flags 0x1
  // signature (II)Z
  // declaration: boolean isSortChannelPositionNull(int, int)
  public isSortChannelPositionNull(II)Z
   L0
    NEW java/lang/UnsupportedOperationException
    DUP
    INVOKESPECIAL java/lang/UnsupportedOperationException.<init> ()V
    ATHROW
   L1
    LOCALVARIABLE this Lcom/facebook/presto/$gen/PagesHashStrategy_20180321_072335_14737; L0 L1 0
    // signature Lcom/facebook/presto/$gen/PagesHashStrategy_20180321_072335_14737;
    // declaration: com.facebook.presto.$gen.PagesHashStrategy_20180321_072335_14737
    LOCALVARIABLE blockIndex I L0 L1 1
    // signature I
    // declaration: int
    LOCALVARIABLE blockPosition I L0 L1 2
    // signature I
    // declaration: int
    MAXSTACK = -1
    MAXLOCALS = -1
}
', isError=false}, FailureType{failureName='com.facebook.presto.client.FailureInfo$FailureException', failureDetail='Error processing class definition:
// class version 52.0 (52)
// access flags 0x31
public final class com/facebook/presto/$gen/PagesHashStrategy_20180321_072337_14757 implements com/facebook/presto/operator/PagesHashStrategy  {


  // access flags 0x1A
  // signature J
  // declaration: long
  private final static J INSTANCE_SIZE

  // access flags 0x12
  // signature J
  // declaration: long
  private final J size

  // access flags 0x12
  // signature Ljava/util/List<Lcom/facebook/presto/spi/block/Block;>;
  // declaration: java.util.List<com.facebook.presto.spi.block.Block>
  private final Ljava/util/List; channel_0

  // access flags 0x12
  // signature Ljava/util/List<Lcom/facebook/presto/spi/block/Block;>;
  // declaration: java.util.List<com.facebook.presto.spi.block.Block>
  private final Ljava/util/List; channel_1

  // access flags 0x12
  // signature Ljava/util/List<Lcom/facebook/presto/spi/block/Block;>;
  // declaration: java.util.List<com.facebook.presto.spi.block.Block>
  private final Ljava/util/List; joinChannel_0

  // access flags 0x12
  // signature Ljava/util/List<Lcom/facebook/presto/spi/block/Block;>;
  // declaration: java.util.List<com.facebook.presto.spi.block.Block>
  private final Ljava/util/List; hashChannel

  // access flags 0x8
  // signature ()V
  // declaration: void <clinit>()
  static <clinit>()V
   L0
    LDC Lcom/facebook/presto/$gen/PagesHashStrategy_20180321_072337_14757;.class
    INVOKESTATIC org/openjdk/jol/info/ClassLayout.parseClass (Ljava/lang/Class;)Lorg/openjdk/jol/info/ClassLayout;
    INVOKEVIRTUAL org/openjdk/jol/info/ClassLayout.instanceSize ()I
    I2L
    PUTSTATIC com/facebook/presto/$gen/PagesHashStrategy_20180321_072337_14757.INSTANCE_SIZE : J
    RETURN
   L1
    MAXSTACK = -1
    MAXLOCALS = -1

  // access flags 0x1
  // signature (Ljava/util/List<Ljava/util/List<Lcom/facebook/presto/spi/block/Block;>;>;Ljava/util/OptionalInt;)V
  // declaration: void <init>(java.util.List<java.util.List<com.facebook.presto.spi.block.Block>>, java.util.OptionalInt)
  public <init>(Ljava/util/List;Ljava/util/OptionalInt;)V
   L0
    ALOAD 0
    INVOKESPECIAL java/lang/Object.<init> ()V
    ALOAD 0
    GETSTATIC com/facebook/presto/$gen/PagesHashStrategy_20180321_072337_14757.INSTANCE_SIZE : J
    PUTFIELD com/facebook/presto/$gen/PagesHashStrategy_20180321_072337_14757.size : J
    ALOAD 0
    ALOAD 1
    ICONST_0
    INVOKEINTERFACE java/util/List.get (I)Ljava/lang/Object;
    CHECKCAST java/util/List
    PUTFIELD com/facebook/presto/$gen/PagesHashStrategy_20180321_072337_14757.channel_0 : Ljava/util/List;
    ICONST_0
    ISTORE 3
   L1
    ILOAD 3
    ALOAD 1
    ICONST_0
    INVOKEINTERFACE java/util/List.get (I)Ljava/lang/Object;
    CHECKCAST java/util/List
    INVOKEINTERFACE java/util/List.size ()I
    INVOKESTATIC com/facebook/presto/sql/gen/CompilerOperations.lessThan (II)Z
    IFEQ L2
    ALOAD 0
    ALOAD 0
    GETFIELD com/facebook/presto/$gen/PagesHashStrategy_20180321_072337_14757.size : J
    ALOAD 1
    ICONST_0
    INVOKEINTERFACE java/util/List.get (I)Ljava/lang/Object;
    CHECKCAST java/util/List
    ILOAD 3
    INVOKEINTERFACE java/util/List.get (I)Ljava/lang/Object;
    CHECKCAST com/facebook/presto/spi/block/Block
    INVOKEINTERFACE com/facebook/presto/spi/block/Block.getRetainedSizeInBytes ()J
    LADD
    PUTFIELD com/facebook/presto/$gen/PagesHashStrategy_20180321_072337_14757.size : J
   L3
    IINC 3 1
    GOTO L1
   L2
    ALOAD 0
    ALOAD 1
    ICONST_1
    INVOKEINTERFACE java/util/List.get (I)Ljava/lang/Object;
    CHECKCAST java/util/List
    PUTFIELD com/facebook/presto/$gen/PagesHashStrategy_20180321_072337_14757.channel_1 : Ljava/util/List;
    ICONST_0
    ISTORE 3
   L4
    ILOAD 3
    ALOAD 1
    ICONST_1
    INVOKEINTERFACE java/util/List.get (I)Ljava/lang/Object;
    CHECKCAST java/util/List
    INVOKEINTERFACE java/util/List.size ()I
    INVOKESTATIC com/facebook/presto/sql/gen/CompilerOperations.lessThan (II)Z
    IFEQ L5
    ALOAD 0
    ALOAD 0
    GETFIELD com/facebook/presto/$gen/PagesHashStrategy_20180321_072337_14757.size : J
    ALOAD 1
    ICONST_1
    INVOKEINTERFACE java/util/List.get (I)Ljava/lang/Object;
    CHECKCAST java/util/List
    ILOAD 3
    INVOKEINTERFACE java/util/List.get (I)Ljava/lang/Object;
    CHECKCAST com/facebook/presto/spi/block/Block
    INVOKEINTERFACE com/facebook/presto/spi/block/Block.getRetainedSizeInBytes ()J
    LADD
    PUTFIELD com/facebook/presto/$gen/PagesHashStrategy_20180321_072337_14757.size : J
   L6
    IINC 3 1
    GOTO L4
   L5
    ALOAD 0
    ALOAD 1
    ICONST_0
    INVOKEINTERFACE java/util/List.get (I)Ljava/lang/Object;
    CHECKCAST java/util/List
    PUTFIELD com/facebook/presto/$gen/PagesHashStrategy_20180321_072337_14757.joinChannel_0 : Ljava/util/List;
    ALOAD 2
    INVOKEVIRTUAL java/util/OptionalInt.isPresent ()Z
    IFEQ L7
    ALOAD 0
    ALOAD 1
    ALOAD 2
    INVOKEVIRTUAL java/util/OptionalInt.getAsInt ()I
    INVOKEINTERFACE java/util/List.get (I)Ljava/lang/Object;
    PUTFIELD com/facebook/presto/$gen/PagesHashStrategy_20180321_072337_14757.hashChannel : Ljava/util/List;
    GOTO L8
   L7
    ALOAD 0
    ACONST_NULL
    PUTFIELD com/facebook/presto/$gen/PagesHashStrategy_20180321_072337_14757.hashChannel : Ljava/util/List;
   L8
    RETURN
   L9
    LOCALVARIABLE this Lcom/facebook/presto/$gen/PagesHashStrategy_20180321_072337_14757; L0 L9 0
    // signature Lcom/facebook/presto/$gen/PagesHashStrategy_20180321_072337_14757;
    // declaration: com.facebook.presto.$gen.PagesHashStrategy_20180321_072337_14757
    LOCALVARIABLE channels Ljava/util/List; L0 L9 1
    // signature Ljava/util/List<Ljava/util/List<Lcom/facebook/presto/spi/block/Block;>;>;
    // declaration: java.util.List<java.util.List<com.facebook.presto.spi.block.Block>>
    LOCALVARIABLE hashChannel Ljava/util/OptionalInt; L0 L9 2
    // signature Ljava/util/OptionalInt;
    // declaration: java.util.OptionalInt
    LOCALVARIABLE blockIndex I L0 L9 3
    // signature I
    // declaration: int
    MAXSTACK = -1
    MAXLOCALS = -1

  // access flags 0x1
  // signature ()I
  // declaration: int getChannelCount()
  public getChannelCount()I
   L0
    ICONST_2
    IRETURN
   L1
    LOCALVARIABLE this Lcom/facebook/presto/$gen/PagesHashStrategy_20180321_072337_14757; L0 L1 0
    // signature Lcom/facebook/presto/$gen/PagesHashStrategy_20180321_072337_14757;
    // declaration: com.facebook.presto.$gen.PagesHashStrategy_20180321_072337_14757
    MAXSTACK = -1
    MAXLOCALS = -1

  // access flags 0x1
  // signature ()J
  // declaration: long getSizeInBytes()
  public getSizeInBytes()J
   L0
    ALOAD 0
    GETFIELD com/facebook/presto/$gen/PagesHashStrategy_20180321_072337_14757.size : J
    LRETURN
   L1
    LOCALVARIABLE this Lcom/facebook/presto/$gen/PagesHashStrategy_20180321_072337_14757; L0 L1 0
    // signature Lcom/facebook/presto/$gen/PagesHashStrategy_20180321_072337_14757;
    // declaration: com.facebook.presto.$gen.PagesHashStrategy_20180321_072337_14757
    MAXSTACK = -1
    MAXLOCALS = -1

  // access flags 0x1
  // signature (IILcom/facebook/presto/spi/PageBuilder;I)V
  // declaration: void appendTo(int, int, com.facebook.presto.spi.PageBuilder, int)
  public appendTo(IILcom/facebook/presto/spi/PageBuilder;I)V
   L0
    INVOKEDYNAMIC array_varchar_1_()Lcom/facebook/presto/spi/type/Type; [
      // handle kind 0x6 : INVOKESTATIC
      com/facebook/presto/sql/gen/Bootstrap.bootstrap(Ljava/lang/invoke/MethodHandles$Lookup;Ljava/lang/String;Ljava/lang/invoke/MethodType;J)Ljava/lang/invoke/CallSite;
      // arguments:
      0
    ]
    ALOAD 0
    GETFIELD com/facebook/presto/$gen/PagesHashStrategy_20180321_072337_14757.channel_0 : Ljava/util/List;
    ILOAD 1
    INVOKEINTERFACE java/util/List.get (I)Ljava/lang/Object;
    CHECKCAST com/facebook/presto/spi/block/Block
    ILOAD 2
    ALOAD 3
    ILOAD 4
    ICONST_0
    IADD
    INVOKEVIRTUAL com/facebook/presto/spi/PageBuilder.getBlockBuilder (I)Lcom/facebook/presto/spi/block/BlockBuilder;
    INVOKEINTERFACE com/facebook/presto/spi/type/Type.appendTo (Lcom/facebook/presto/spi/block/Block;ILcom/facebook/presto/spi/block/BlockBuilder;)V
    INVOKEDYNAMIC bigint()Lcom/facebook/presto/spi/type/Type; [
      // handle kind 0x6 : INVOKESTATIC
      com/facebook/presto/sql/gen/Bootstrap.bootstrap(Ljava/lang/invoke/MethodHandles$Lookup;Ljava/lang/String;Ljava/lang/invoke/MethodType;J)Ljava/lang/invoke/CallSite;
      // arguments:
      1
    ]
    ALOAD 0
    GETFIELD com/facebook/presto/$gen/PagesHashStrategy_20180321_072337_14757.channel_1 : Ljava/util/List;
    ILOAD 1
    INVOKEINTERFACE java/util/List.get (I)Ljava/lang/Object;
    CHECKCAST com/facebook/presto/spi/block/Block
    ILOAD 2
    ALOAD 3
    ILOAD 4
    ICONST_1
    IADD
    INVOKEVIRTUAL com/facebook/presto/spi/PageBuilder.getBlockBuilder (I)Lcom/facebook/presto/spi/block/BlockBuilder;
    INVOKEINTERFACE com/facebook/presto/spi/type/Type.appendTo (Lcom/facebook/presto/spi/block/Block;ILcom/facebook/presto/spi/block/BlockBuilder;)V
    RETURN
   L1
    LOCALVARIABLE this Lcom/facebook/presto/$gen/PagesHashStrategy_20180321_072337_14757; L0 L1 0
    // signature Lcom/facebook/presto/$gen/PagesHashStrategy_20180321_072337_14757;
    // declaration: com.facebook.presto.$gen.PagesHashStrategy_20180321_072337_14757
    LOCALVARIABLE blockIndex I L0 L1 1
    // signature I
    // declaration: int
    LOCALVARIABLE blockPosition I L0 L1 2
    // signature I
    // declaration: int
    LOCALVARIABLE pageBuilder Lcom/facebook/presto/spi/PageBuilder; L0 L1 3
    // signature Lcom/facebook/presto/spi/PageBuilder;
    // declaration: com.facebook.presto.spi.PageBuilder
    LOCALVARIABLE outputChannelOffset I L0 L1 4
    // signature I
    // declaration: int
    MAXSTACK = -1
    MAXLOCALS = -1

  // access flags 0x1
  // signature (II)J
  // declaration: long hashPosition(int, int)
  public hashPosition(II)J
   L0
    ALOAD 0
    GETFIELD com/facebook/presto/$gen/PagesHashStrategy_20180321_072337_14757.hashChannel : Ljava/util/List;
    ACONST_NULL
    IF_ACMPEQ L1
    ICONST_1
    GOTO L2
   L1
    ICONST_0
   L2
    IFEQ L3
    INVOKEDYNAMIC bigint()Lcom/facebook/presto/spi/type/Type; [
      // handle kind 0x6 : INVOKESTATIC
      com/facebook/presto/sql/gen/Bootstrap.bootstrap(Ljava/lang/invoke/MethodHandles$Lookup;Ljava/lang/String;Ljava/lang/invoke/MethodType;J)Ljava/lang/invoke/CallSite;
      // arguments:
      2
    ]
    ALOAD 0
    GETFIELD com/facebook/presto/$gen/PagesHashStrategy_20180321_072337_14757.hashChannel : Ljava/util/List;
    ILOAD 1
    INVOKEINTERFACE java/util/List.get (I)Ljava/lang/Object;
    CHECKCAST com/facebook/presto/spi/block/Block
    ILOAD 2
    INVOKEINTERFACE com/facebook/presto/spi/type/Type.getLong (Lcom/facebook/presto/spi/block/Block;I)J
    LRETURN
   L3
    LCONST_0
    LSTORE 3
    LLOAD 3
    LDC 31
    LMUL
    ALOAD 0
    GETFIELD com/facebook/presto/$gen/PagesHashStrategy_20180321_072337_14757.joinChannel_0 : Ljava/util/List;
    ILOAD 1
    INVOKEINTERFACE java/util/List.get (I)Ljava/lang/Object;
    CHECKCAST com/facebook/presto/spi/block/Block
    ILOAD 2
    INVOKEINTERFACE com/facebook/presto/spi/block/Block.isNull (I)Z
    IFEQ L4
    LCONST_0
    GOTO L5
   L4
    INVOKEDYNAMIC array_varchar_1_()Lcom/facebook/presto/spi/type/Type; [
      // handle kind 0x6 : INVOKESTATIC
      com/facebook/presto/sql/gen/Bootstrap.bootstrap(Ljava/lang/invoke/MethodHandles$Lookup;Ljava/lang/String;Ljava/lang/invoke/MethodType;J)Ljava/lang/invoke/CallSite;
      // arguments:
      3
    ]
    ALOAD 0
    GETFIELD com/facebook/presto/$gen/PagesHashStrategy_20180321_072337_14757.joinChannel_0 : Ljava/util/List;
    ILOAD 1
    INVOKEINTERFACE java/util/List.get (I)Ljava/lang/Object;
    CHECKCAST com/facebook/presto/spi/block/Block
    ILOAD 2
    INVOKEINTERFACE com/facebook/presto/spi/type/Type.hash (Lcom/facebook/presto/spi/block/Block;I)J
   L5
    LADD
    LSTORE 3
    LLOAD 3
    LRETURN
   L6
    LOCALVARIABLE this Lcom/facebook/presto/$gen/PagesHashStrategy_20180321_072337_14757; L0 L6 0
    // signature Lcom/facebook/presto/$gen/PagesHashStrategy_20180321_072337_14757;
    // declaration: com.facebook.presto.$gen.PagesHashStrategy_20180321_072337_14757
    LOCALVARIABLE blockIndex I L0 L6 1
    // signature I
    // declaration: int
    LOCALVARIABLE blockPosition I L0 L6 2
    // signature I
    // declaration: int
    LOCALVARIABLE result J L0 L6 3
    // signature J
    // declaration: long
    MAXSTACK = -1
    MAXLOCALS = -1

  // access flags 0x1
  // signature (ILcom/facebook/presto/spi/Page;)J
  // declaration: long hashRow(int, com.facebook.presto.spi.Page)
  public hashRow(ILcom/facebook/presto/spi/Page;)J
   L0
    LCONST_0
    LSTORE 3
    LLOAD 3
    LDC 31
    LMUL
    ALOAD 2
    ICONST_0
    INVOKEVIRTUAL com/facebook/presto/spi/Page.getBlock (I)Lcom/facebook/presto/spi/block/Block;
    ILOAD 1
    INVOKEINTERFACE com/facebook/presto/spi/block/Block.isNull (I)Z
    IFEQ L1
    LCONST_0
    GOTO L2
   L1
    INVOKEDYNAMIC array_varchar_1_()Lcom/facebook/presto/spi/type/Type; [
      // handle kind 0x6 : INVOKESTATIC
      com/facebook/presto/sql/gen/Bootstrap.bootstrap(Ljava/lang/invoke/MethodHandles$Lookup;Ljava/lang/String;Ljava/lang/invoke/MethodType;J)Ljava/lang/invoke/CallSite;
      // arguments:
      4
    ]
    ALOAD 2
    ICONST_0
    INVOKEVIRTUAL com/facebook/presto/spi/Page.getBlock (I)Lcom/facebook/presto/spi/block/Block;
    ILOAD 1
    INVOKEINTERFACE com/facebook/presto/spi/type/Type.hash (Lcom/facebook/presto/spi/block/Block;I)J
   L2
    LADD
    LSTORE 3
    LLOAD 3
    LRETURN
   L3
    LOCALVARIABLE this Lcom/facebook/presto/$gen/PagesHashStrategy_20180321_072337_14757; L0 L3 0
    // signature Lcom/facebook/presto/$gen/PagesHashStrategy_20180321_072337_14757;
    // declaration: com.facebook.presto.$gen.PagesHashStrategy_20180321_072337_14757
    LOCALVARIABLE position I L0 L3 1
    // signature I
    // declaration: int
    LOCALVARIABLE blocks Lcom/facebook/presto/spi/Page; L0 L3 2
    // signature Lcom/facebook/presto/spi/Page;
    // declaration: com.facebook.presto.spi.Page
    LOCALVARIABLE result J L0 L3 3
    // signature J
    // declaration: long
    MAXSTACK = -1
    MAXLOCALS = -1

  // access flags 0x1
  // signature (ILcom/facebook/presto/spi/Page;ILcom/facebook/presto/spi/Page;)Z
  // declaration: boolean rowEqualsRow(int, com.facebook.presto.spi.Page, int, com.facebook.presto.spi.Page)
  public rowEqualsRow(ILcom/facebook/presto/spi/Page;ILcom/facebook/presto/spi/Page;)Z
   L0
    ALOAD 2
    ICONST_0
    INVOKEVIRTUAL com/facebook/presto/spi/Page.getBlock (I)Lcom/facebook/presto/spi/block/Block;
    ILOAD 1
    INVOKEINTERFACE com/facebook/presto/spi/block/Block.isNull (I)Z
    ALOAD 4
    ICONST_0
    INVOKEVIRTUAL com/facebook/presto/spi/Page.getBlock (I)Lcom/facebook/presto/spi/block/Block;
    ILOAD 3
    INVOKEINTERFACE com/facebook/presto/spi/block/Block.isNull (I)Z
    IOR
    IFEQ L1
    ALOAD 2
    ICONST_0
    INVOKEVIRTUAL com/facebook/presto/spi/Page.getBlock (I)Lcom/facebook/presto/spi/block/Block;
    ILOAD 1
    INVOKEINTERFACE com/facebook/presto/spi/block/Block.isNull (I)Z
    ALOAD 4
    ICONST_0
    INVOKEVIRTUAL com/facebook/presto/spi/Page.getBlock (I)Lcom/facebook/presto/spi/block/Block;
    ILOAD 3
    INVOKEINTERFACE com/facebook/presto/spi/block/Block.isNull (I)Z
    IAND
    GOTO L2
   L1
    INVOKEDYNAMIC array_varchar_1_()Lcom/facebook/presto/spi/type/Type; [
      // handle kind 0x6 : INVOKESTATIC
      com/facebook/presto/sql/gen/Bootstrap.bootstrap(Ljava/lang/invoke/MethodHandles$Lookup;Ljava/lang/String;Ljava/lang/invoke/MethodType;J)Ljava/lang/invoke/CallSite;
      // arguments:
      5
    ]
    ALOAD 2
    ICONST_0
    INVOKEVIRTUAL com/facebook/presto/spi/Page.getBlock (I)Lcom/facebook/presto/spi/block/Block;
    ILOAD 1
    ALOAD 4
    ICONST_0
    INVOKEVIRTUAL com/facebook/presto/spi/Page.getBlock (I)Lcom/facebook/presto/spi/block/Block;
    ILOAD 3
    INVOKEINTERFACE com/facebook/presto/spi/type/Type.equalTo (Lcom/facebook/presto/spi/block/Block;ILcom/facebook/presto/spi/block/Block;I)Z
   L2
    IFNE L3
    ICONST_0
    IRETURN
   L3
    ICONST_1
    IRETURN
   L4
    LOCALVARIABLE this Lcom/facebook/presto/$gen/PagesHashStrategy_20180321_072337_14757; L0 L4 0
    // signature Lcom/facebook/presto/$gen/PagesHashStrategy_20180321_072337_14757;
    // declaration: com.facebook.presto.$gen.PagesHashStrategy_20180321_072337_14757
    LOCALVARIABLE leftPosition I L0 L4 1
    // signature I
    // declaration: int
    LOCALVARIABLE leftPage Lcom/facebook/presto/spi/Page; L0 L4 2
    // signature Lcom/facebook/presto/spi/Page;
    // declaration: com.facebook.presto.spi.Page
    LOCALVARIABLE rightPosition I L0 L4 3
    // signature I
    // declaration: int
    LOCALVARIABLE rightPage Lcom/facebook/presto/spi/Page; L0 L4 4
    // signature Lcom/facebook/presto/spi/Page;
    // declaration: com.facebook.presto.spi.Page
    MAXSTACK = -1
    MAXLOCALS = -1

  // access flags 0x1
  // signature (IIILcom/facebook/presto/spi/Page;)Z
  // declaration: boolean positionEqualsRowIgnoreNulls(int, int, int, com.facebook.presto.spi.Page)
  public positionEqualsRowIgnoreNulls(IIILcom/facebook/presto/spi/Page;)Z
   L0
    INVOKEDYNAMIC array_varchar_1_()Lcom/facebook/presto/spi/type/Type; [
      // handle kind 0x6 : INVOKESTATIC
      com/facebook/presto/sql/gen/Bootstrap.bootstrap(Ljava/lang/invoke/MethodHandles$Lookup;Ljava/lang/String;Ljava/lang/invoke/MethodType;J)Ljava/lang/invoke/CallSite;
      // arguments:
      6
    ]
    ALOAD 0
    GETFIELD com/facebook/presto/$gen/PagesHashStrategy_20180321_072337_14757.joinChannel_0 : Ljava/util/List;
    ILOAD 1
    INVOKEINTERFACE java/util/List.get (I)Ljava/lang/Object;
    CHECKCAST com/facebook/presto/spi/block/Block
    ILOAD 2
    ALOAD 4
    ICONST_0
    INVOKEVIRTUAL com/facebook/presto/spi/Page.getBlock (I)Lcom/facebook/presto/spi/block/Block;
    ILOAD 3
    INVOKEINTERFACE com/facebook/presto/spi/type/Type.equalTo (Lcom/facebook/presto/spi/block/Block;ILcom/facebook/presto/spi/block/Block;I)Z
    IFNE L1
    ICONST_0
    IRETURN
   L1
    ICONST_1
    IRETURN
   L2
    LOCALVARIABLE this Lcom/facebook/presto/$gen/PagesHashStrategy_20180321_072337_14757; L0 L2 0
    // signature Lcom/facebook/presto/$gen/PagesHashStrategy_20180321_072337_14757;
    // declaration: com.facebook.presto.$gen.PagesHashStrategy_20180321_072337_14757
    LOCALVARIABLE leftBlockIndex I L0 L2 1
    // signature I
    // declaration: int
    LOCALVARIABLE leftBlockPosition I L0 L2 2
    // signature I
    // declaration: int
    LOCALVARIABLE rightPosition I L0 L2 3
    // signature I
    // declaration: int
    LOCALVARIABLE rightPage Lcom/facebook/presto/spi/Page; L0 L2 4
    // signature Lcom/facebook/presto/spi/Page;
    // declaration: com.facebook.presto.spi.Page
    MAXSTACK = -1
    MAXLOCALS = -1

  // access flags 0x1
  // signature (IIILcom/facebook/presto/spi/Page;)Z
  // declaration: boolean positionEqualsRow(int, int, int, com.facebook.presto.spi.Page)
  public positionEqualsRow(IIILcom/facebook/presto/spi/Page;)Z
   L0
    ALOAD 0
    GETFIELD com/facebook/presto/$gen/PagesHashStrategy_20180321_072337_14757.joinChannel_0 : Ljava/util/List;
    ILOAD 1
    INVOKEINTERFACE java/util/List.get (I)Ljava/lang/Object;
    CHECKCAST com/facebook/presto/spi/block/Block
    ILOAD 2
    INVOKEINTERFACE com/facebook/presto/spi/block/Block.isNull (I)Z
    ALOAD 4
    ICONST_0
    INVOKEVIRTUAL com/facebook/presto/spi/Page.getBlock (I)Lcom/facebook/presto/spi/block/Block;
    ILOAD 3
    INVOKEINTERFACE com/facebook/presto/spi/block/Block.isNull (I)Z
    IOR
    IFEQ L1
    ALOAD 0
    GETFIELD com/facebook/presto/$gen/PagesHashStrategy_20180321_072337_14757.joinChannel_0 : Ljava/util/List;
    ILOAD 1
    INVOKEINTERFACE java/util/List.get (I)Ljava/lang/Object;
    CHECKCAST com/facebook/presto/spi/block/Block
    ILOAD 2
    INVOKEINTERFACE com/facebook/presto/spi/block/Block.isNull (I)Z
    ALOAD 4
    ICONST_0
    INVOKEVIRTUAL com/facebook/presto/spi/Page.getBlock (I)Lcom/facebook/presto/spi/block/Block;
    ILOAD 3
    INVOKEINTERFACE com/facebook/presto/spi/block/Block.isNull (I)Z
    IAND
    GOTO L2
   L1
    INVOKEDYNAMIC array_varchar_1_()Lcom/facebook/presto/spi/type/Type; [
      // handle kind 0x6 : INVOKESTATIC
      com/facebook/presto/sql/gen/Bootstrap.bootstrap(Ljava/lang/invoke/MethodHandles$Lookup;Ljava/lang/String;Ljava/lang/invoke/MethodType;J)Ljava/lang/invoke/CallSite;
      // arguments:
      7
    ]
    ALOAD 0
    GETFIELD com/facebook/presto/$gen/PagesHashStrategy_20180321_072337_14757.joinChannel_0 : Ljava/util/List;
    ILOAD 1
    INVOKEINTERFACE java/util/List.get (I)Ljava/lang/Object;
    CHECKCAST com/facebook/presto/spi/block/Block
    ILOAD 2
    ALOAD 4
    ICONST_0
    INVOKEVIRTUAL com/facebook/presto/spi/Page.getBlock (I)Lcom/facebook/presto/spi/block/Block;
    ILOAD 3
    INVOKEINTERFACE com/facebook/presto/spi/type/Type.equalTo (Lcom/facebook/presto/spi/block/Block;ILcom/facebook/presto/spi/block/Block;I)Z
   L2
    IFNE L3
    ICONST_0
    IRETURN
   L3
    ICONST_1
    IRETURN
   L4
    LOCALVARIABLE this Lcom/facebook/presto/$gen/PagesHashStrategy_20180321_072337_14757; L0 L4 0
    // signature Lcom/facebook/presto/$gen/PagesHashStrategy_20180321_072337_14757;
    // declaration: com.facebook.presto.$gen.PagesHashStrategy_20180321_072337_14757
    LOCALVARIABLE leftBlockIndex I L0 L4 1
    // signature I
    // declaration: int
    LOCALVARIABLE leftBlockPosition I L0 L4 2
    // signature I
    // declaration: int
    LOCALVARIABLE rightPosition I L0 L4 3
    // signature I
    // declaration: int
    LOCALVARIABLE rightPage Lcom/facebook/presto/spi/Page; L0 L4 4
    // signature Lcom/facebook/presto/spi/Page;
    // declaration: com.facebook.presto.spi.Page
    MAXSTACK = -1
    MAXLOCALS = -1

  // access flags 0x1
  // signature (IIILcom/facebook/presto/spi/Page;[I)Z
  // declaration: boolean positionEqualsRow(int, int, int, com.facebook.presto.spi.Page, int[])
  public positionEqualsRow(IIILcom/facebook/presto/spi/Page;[I)Z
   L0
    INVOKEDYNAMIC array_varchar_1_()Lcom/facebook/presto/spi/type/Type; [
      // handle kind 0x6 : INVOKESTATIC
      com/facebook/presto/sql/gen/Bootstrap.bootstrap(Ljava/lang/invoke/MethodHandles$Lookup;Ljava/lang/String;Ljava/lang/invoke/MethodType;J)Ljava/lang/invoke/CallSite;
      // arguments:
      8
    ]
    ALOAD 0
    GETFIELD com/facebook/presto/$gen/PagesHashStrategy_20180321_072337_14757.joinChannel_0 : Ljava/util/List;
    ILOAD 1
    INVOKEINTERFACE java/util/List.get (I)Ljava/lang/Object;
    CHECKCAST com/facebook/presto/spi/block/Block
    ILOAD 2
    INVOKEINTERFACE com/facebook/presto/spi/type/Type.getObject (Lcom/facebook/presto/spi/block/Block;I)Ljava/lang/Object;
    CHECKCAST com/facebook/presto/spi/block/Block
    INVOKEDYNAMIC array_varchar_1_()Lcom/facebook/presto/spi/type/Type; [
      // handle kind 0x6 : INVOKESTATIC
      com/facebook/presto/sql/gen/Bootstrap.bootstrap(Ljava/lang/invoke/MethodHandles$Lookup;Ljava/lang/String;Ljava/lang/invoke/MethodType;J)Ljava/lang/invoke/CallSite;
      // arguments:
      8
    ]
    ALOAD 4
    ALOAD 5
    ICONST_0
    IALOAD
    INVOKEVIRTUAL com/facebook/presto/spi/Page.getBlock (I)Lcom/facebook/presto/spi/block/Block;
    ILOAD 3
    INVOKEINTERFACE com/facebook/presto/spi/type/Type.getObject (Lcom/facebook/presto/spi/block/Block;I)Ljava/lang/Object;
    CHECKCAST com/facebook/presto/spi/block/Block
    INVOKEDYNAMIC $operator$IS_DISTINCT_FROM(Lcom/facebook/presto/spi/block/Block;ZLcom/facebook/presto/spi/block/Block;Z)Z [
      // handle kind 0x6 : INVOKESTATIC
      com/facebook/presto/sql/gen/Bootstrap.bootstrap(Ljava/lang/invoke/MethodHandles$Lookup;Ljava/lang/String;Ljava/lang/invoke/MethodType;J)Ljava/lang/invoke/CallSite;
      // arguments:
      9
    ]
   L1
    IFEQ L2
    ICONST_0
    IRETURN
   L2
    ICONST_1
    IRETURN
   L3
    LOCALVARIABLE this Lcom/facebook/presto/$gen/PagesHashStrategy_20180321_072337_14757; L0 L3 0
    // signature Lcom/facebook/presto/$gen/PagesHashStrategy_20180321_072337_14757;
    // declaration: com.facebook.presto.$gen.PagesHashStrategy_20180321_072337_14757
    LOCALVARIABLE leftBlockIndex I L0 L3 1
    // signature I
    // declaration: int
    LOCALVARIABLE leftBlockPosition I L0 L3 2
    // signature I
    // declaration: int
    LOCALVARIABLE rightPosition I L0 L3 3
    // signature I
    // declaration: int
    LOCALVARIABLE page Lcom/facebook/presto/spi/Page; L0 L3 4
    // signature Lcom/facebook/presto/spi/Page;
    // declaration: com.facebook.presto.spi.Page
    LOCALVARIABLE rightChannels [I L0 L3 5
    // signature [I
    // declaration: int[]
    MAXSTACK = -1
    MAXLOCALS = -1

  // access flags 0x1
  // signature (IIII)Z
  // declaration: boolean positionEqualsPositionIgnoreNulls(int, int, int, int)
  public positionEqualsPositionIgnoreNulls(IIII)Z
   L0
    INVOKEDYNAMIC array_varchar_1_()Lcom/facebook/presto/spi/type/Type; [
      // handle kind 0x6 : INVOKESTATIC
      com/facebook/presto/sql/gen/Bootstrap.bootstrap(Ljava/lang/invoke/MethodHandles$Lookup;Ljava/lang/String;Ljava/lang/invoke/MethodType;J)Ljava/lang/invoke/CallSite;
      // arguments:
      10
    ]
    ALOAD 0
    GETFIELD com/facebook/presto/$gen/PagesHashStrategy_20180321_072337_14757.joinChannel_0 : Ljava/util/List;
    ILOAD 1
    INVOKEINTERFACE java/util/List.get (I)Ljava/lang/Object;
    CHECKCAST com/facebook/presto/spi/block/Block
    ILOAD 2
    ALOAD 0
    GETFIELD com/facebook/presto/$gen/PagesHashStrategy_20180321_072337_14757.joinChannel_0 : Ljava/util/List;
    ILOAD 3
    INVOKEINTERFACE java/util/List.get (I)Ljava/lang/Object;
    CHECKCAST com/facebook/presto/spi/block/Block
    ILOAD 4
    INVOKEINTERFACE com/facebook/presto/spi/type/Type.equalTo (Lcom/facebook/presto/spi/block/Block;ILcom/facebook/presto/spi/block/Block;I)Z
    IFNE L1
    ICONST_0
    IRETURN
   L1
    ICONST_1
    IRETURN
   L2
    LOCALVARIABLE this Lcom/facebook/presto/$gen/PagesHashStrategy_20180321_072337_14757; L0 L2 0
    // signature Lcom/facebook/presto/$gen/PagesHashStrategy_20180321_072337_14757;
    // declaration: com.facebook.presto.$gen.PagesHashStrategy_20180321_072337_14757
    LOCALVARIABLE leftBlockIndex I L0 L2 1
    // signature I
    // declaration: int
    LOCALVARIABLE leftBlockPosition I L0 L2 2
    // signature I
    // declaration: int
    LOCALVARIABLE rightBlockIndex I L0 L2 3
    // signature I
    // declaration: int
    LOCALVARIABLE rightBlockPosition I L0 L2 4
    // signature I
    // declaration: int
    MAXSTACK = -1
    MAXLOCALS = -1

  // access flags 0x1
  // signature (IIII)Z
  // declaration: boolean positionEqualsPosition(int, int, int, int)
  public positionEqualsPosition(IIII)Z
   L0
    ALOAD 0
    GETFIELD com/facebook/presto/$gen/PagesHashStrategy_20180321_072337_14757.joinChannel_0 : Ljava/util/List;
    ILOAD 1
    INVOKEINTERFACE java/util/List.get (I)Ljava/lang/Object;
    CHECKCAST com/facebook/presto/spi/block/Block
    ILOAD 2
    INVOKEINTERFACE com/facebook/presto/spi/block/Block.isNull (I)Z
    ALOAD 0
    GETFIELD com/facebook/presto/$gen/PagesHashStrategy_20180321_072337_14757.joinChannel_0 : Ljava/util/List;
    ILOAD 3
    INVOKEINTERFACE java/util/List.get (I)Ljava/lang/Object;
    CHECKCAST com/facebook/presto/spi/block/Block
    ILOAD 4
    INVOKEINTERFACE com/facebook/presto/spi/block/Block.isNull (I)Z
    IOR
    IFEQ L1
    ALOAD 0
    GETFIELD com/facebook/presto/$gen/PagesHashStrategy_20180321_072337_14757.joinChannel_0 : Ljava/util/List;
    ILOAD 1
    INVOKEINTERFACE java/util/List.get (I)Ljava/lang/Object;
    CHECKCAST com/facebook/presto/spi/block/Block
    ILOAD 2
    INVOKEINTERFACE com/facebook/presto/spi/block/Block.isNull (I)Z
    ALOAD 0
    GETFIELD com/facebook/presto/$gen/PagesHashStrategy_20180321_072337_14757.joinChannel_0 : Ljava/util/List;
    ILOAD 3
    INVOKEINTERFACE java/util/List.get (I)Ljava/lang/Object;
    CHECKCAST com/facebook/presto/spi/block/Block
    ILOAD 4
    INVOKEINTERFACE com/facebook/presto/spi/block/Block.isNull (I)Z
    IAND
    GOTO L2
   L1
    INVOKEDYNAMIC array_varchar_1_()Lcom/facebook/presto/spi/type/Type; [
      // handle kind 0x6 : INVOKESTATIC
      com/facebook/presto/sql/gen/Bootstrap.bootstrap(Ljava/lang/invoke/MethodHandles$Lookup;Ljava/lang/String;Ljava/lang/invoke/MethodType;J)Ljava/lang/invoke/CallSite;
      // arguments:
      11
    ]
    ALOAD 0
    GETFIELD com/facebook/presto/$gen/PagesHashStrategy_20180321_072337_14757.joinChannel_0 : Ljava/util/List;
    ILOAD 1
    INVOKEINTERFACE java/util/List.get (I)Ljava/lang/Object;
    CHECKCAST com/facebook/presto/spi/block/Block
    ILOAD 2
    ALOAD 0
    GETFIELD com/facebook/presto/$gen/PagesHashStrategy_20180321_072337_14757.joinChannel_0 : Ljava/util/List;
    ILOAD 3
    INVOKEINTERFACE java/util/List.get (I)Ljava/lang/Object;
    CHECKCAST com/facebook/presto/spi/block/Block
    ILOAD 4
    INVOKEINTERFACE com/facebook/presto/spi/type/Type.equalTo (Lcom/facebook/presto/spi/block/Block;ILcom/facebook/presto/spi/block/Block;I)Z
   L2
    IFNE L3
    ICONST_0
    IRETURN
   L3
    ICONST_1
    IRETURN
   L4
    LOCALVARIABLE this Lcom/facebook/presto/$gen/PagesHashStrategy_20180321_072337_14757; L0 L4 0
    // signature Lcom/facebook/presto/$gen/PagesHashStrategy_20180321_072337_14757;
    // declaration: com.facebook.presto.$gen.PagesHashStrategy_20180321_072337_14757
    LOCALVARIABLE leftBlockIndex I L0 L4 1
    // signature I
    // declaration: int
    LOCALVARIABLE leftBlockPosition I L0 L4 2
    // signature I
    // declaration: int
    LOCALVARIABLE rightBlockIndex I L0 L4 3
    // signature I
    // declaration: int
    LOCALVARIABLE rightBlockPosition I L0 L4 4
    // signature I
    // declaration: int
    MAXSTACK = -1
    MAXLOCALS = -1

  // access flags 0x1
  // signature (II)Z
  // declaration: boolean isPositionNull(int, int)
  public isPositionNull(II)Z
   L0
    ALOAD 0
    GETFIELD com/facebook/presto/$gen/PagesHashStrategy_20180321_072337_14757.joinChannel_0 : Ljava/util/List;
    ILOAD 1
    INVOKEINTERFACE java/util/List.get (I)Ljava/lang/Object;
    CHECKCAST com/facebook/presto/spi/block/Block
    ILOAD 2
    INVOKEINTERFACE com/facebook/presto/spi/block/Block.isNull (I)Z
    IFEQ L1
    ICONST_1
    IRETURN
   L1
    ICONST_0
    IRETURN
   L2
    LOCALVARIABLE this Lcom/facebook/presto/$gen/PagesHashStrategy_20180321_072337_14757; L0 L2 0
    // signature Lcom/facebook/presto/$gen/PagesHashStrategy_20180321_072337_14757;
    // declaration: com.facebook.presto.$gen.PagesHashStrategy_20180321_072337_14757
    LOCALVARIABLE blockIndex I L0 L2 1
    // signature I
    // declaration: int
    LOCALVARIABLE blockPosition I L0 L2 2
    // signature I
    // declaration: int
    MAXSTACK = -1
    MAXLOCALS = -1

  // access flags 0x1
  // signature (IIII)I
  // declaration: int compareSortChannelPositions(int, int, int, int)
  public compareSortChannelPositions(IIII)I
   L0
    NEW java/lang/UnsupportedOperationException
    DUP
    INVOKESPECIAL java/lang/UnsupportedOperationException.<init> ()V
    ATHROW
   L1
    LOCALVARIABLE this Lcom/facebook/presto/$gen/PagesHashStrategy_20180321_072337_14757; L0 L1 0
    // signature Lcom/facebook/presto/$gen/PagesHashStrategy_20180321_072337_14757;
    // declaration: com.facebook.presto.$gen.PagesHashStrategy_20180321_072337_14757
    LOCALVARIABLE leftBlockIndex I L0 L1 1
    // signature I
    // declaration: int
    LOCALVARIABLE leftBlockPosition I L0 L1 2
    // signature I
    // declaration: int
    LOCALVARIABLE rightBlockIndex I L0 L1 3
    // signature I
    // declaration: int
    LOCALVARIABLE rightBlockPosition I L0 L1 4
    // signature I
    // declaration: int
    MAXSTACK = -1
    MAXLOCALS = -1

  // access flags 0x1
  // signature (II)Z
  // declaration: boolean isSortChannelPositionNull(int, int)
  public isSortChannelPositionNull(II)Z
   L0
    NEW java/lang/UnsupportedOperationException
    DUP
    INVOKESPECIAL java/lang/UnsupportedOperationException.<init> ()V
    ATHROW
   L1
    LOCALVARIABLE this Lcom/facebook/presto/$gen/PagesHashStrategy_20180321_072337_14757; L0 L1 0
    // signature Lcom/facebook/presto/$gen/PagesHashStrategy_20180321_072337_14757;
    // declaration: com.facebook.presto.$gen.PagesHashStrategy_20180321_072337_14757
    LOCALVARIABLE blockIndex I L0 L1 1
    // signature I
    // declaration: int
    LOCALVARIABLE blockPosition I L0 L1 2
    // signature I
    // declaration: int
    MAXSTACK = -1
    MAXLOCALS = -1
}
', isError=false}], nbFailures=2, nbErrors=0}
status: NOPATCH
dateEnd: Wed Mar 21 08:27:05 CET 2018
allocatedtime: 120minutes 
passingTime: 0minutes 
nb patches: 0
nopol context: Config{synthesisDepth=3, collectStaticMethods=true, collectStaticFields=false, collectLiterals=false, onlyOneSynthesisResult=false, sortExpressions=true, maxLineInvocationPerTest=250, timeoutMethodInvocation=2000, dataCollectionTimeoutInSecondForSynthesis=900, addWeight=0.19478, subWeight=0.04554, mulWeight=0.0102, divWeight=0.00613, andWeight=0.10597, orWeight=0.05708, eqWeight=0.22798, nEqWeight=0.0, lessEqWeight=0.0255, lessWeight=0.0947, methodCallWeight=0.1, fieldAccessWeight=0.08099, constantWeight=0.14232, variableWeight=0.05195, mode=REPAIR, type=COND_THEN_PRE, synthesis=DYNAMOTH, oracle=ANGELIC, solver=Z3, solverPath='./z3_for_linux', projectSources=[/root/workspace/prestodb/presto/356202150/presto-tests/src/main/java], projectClasspath='[Ljava.net.URL;@5542418c', projectTests=[com.facebook.presto.memory.TestMemoryManager], complianceLevel=8, outputFolder=./workspace/prestodb/presto/356202150, json=false}
exception: null
nbStatements: 0
nbAngelicValues: 0
ignoreStatus: NOTHING_TO_IGNORE
----------



nopolinfo #3
location: FailureLocation{className='com.facebook.presto.tests.TestAggregations', failingMethods=[com.facebook.presto.tests.TestAggregations#testGroupByArray], erroringMethods=[], failures=[FailureType{failureName='java.lang.AssertionError', failureDetail='Execution of 'actual' query failed: SELECT col[1], count FROM (SELECT ARRAY[custkey] col, COUNT(*) count FROM orders GROUP BY 1 ORDER BY 1)', isError=false}], nbFailures=1, nbErrors=0}
status: NOPATCH
dateEnd: Wed Mar 21 08:27:10 CET 2018
allocatedtime: 120minutes 
passingTime: 0minutes 
nb patches: 0
nopol context: Config{synthesisDepth=3, collectStaticMethods=true, collectStaticFields=false, collectLiterals=false, onlyOneSynthesisResult=false, sortExpressions=true, maxLineInvocationPerTest=250, timeoutMethodInvocation=2000, dataCollectionTimeoutInSecondForSynthesis=900, addWeight=0.19478, subWeight=0.04554, mulWeight=0.0102, divWeight=0.00613, andWeight=0.10597, orWeight=0.05708, eqWeight=0.22798, nEqWeight=0.0, lessEqWeight=0.0255, lessWeight=0.0947, methodCallWeight=0.1, fieldAccessWeight=0.08099, constantWeight=0.14232, variableWeight=0.05195, mode=REPAIR, type=COND_THEN_PRE, synthesis=DYNAMOTH, oracle=ANGELIC, solver=Z3, solverPath='./z3_for_linux', projectSources=[/root/workspace/prestodb/presto/356202150/presto-tests/src/main/java], projectClasspath='[Ljava.net.URL;@8588a62', projectTests=[com.facebook.presto.tests.TestAggregations], complianceLevel=8, outputFolder=./workspace/prestodb/presto/356202150, json=false}
exception: null
nbStatements: 0
nbAngelicValues: 0
ignoreStatus: NOTHING_TO_IGNORE
----------



nopolinfo #4
location: FailureLocation{className='com.facebook.presto.tests.TestIsNotDistinctFrom', failingMethods=[com.facebook.presto.tests.TestIsNotDistinctFrom#testDistinctNan], erroringMethods=[], failures=[FailureType{failureName='com.facebook.presto.spi.PrestoException', failureDetail='Division by zero', isError=false}], nbFailures=1, nbErrors=0}
status: NOPATCH
dateEnd: Wed Mar 21 08:27:14 CET 2018
allocatedtime: 120minutes 
passingTime: 0minutes 
nb patches: 0
nopol context: Config{synthesisDepth=3, collectStaticMethods=true, collectStaticFields=false, collectLiterals=false, onlyOneSynthesisResult=false, sortExpressions=true, maxLineInvocationPerTest=250, timeoutMethodInvocation=2000, dataCollectionTimeoutInSecondForSynthesis=900, addWeight=0.19478, subWeight=0.04554, mulWeight=0.0102, divWeight=0.00613, andWeight=0.10597, orWeight=0.05708, eqWeight=0.22798, nEqWeight=0.0, lessEqWeight=0.0255, lessWeight=0.0947, methodCallWeight=0.1, fieldAccessWeight=0.08099, constantWeight=0.14232, variableWeight=0.05195, mode=REPAIR, type=COND_THEN_PRE, synthesis=DYNAMOTH, oracle=ANGELIC, solver=Z3, solverPath='./z3_for_linux', projectSources=[/root/workspace/prestodb/presto/356202150/presto-tests/src/main/java], projectClasspath='[Ljava.net.URL;@4fa62aed', projectTests=[com.facebook.presto.tests.TestIsNotDistinctFrom], complianceLevel=8, outputFolder=./workspace/prestodb/presto/356202150, json=false}
exception: null
nbStatements: 0
nbAngelicValues: 0
ignoreStatus: NOTHING_TO_IGNORE
----------



nopolinfo #5
location: FailureLocation{className='com.facebook.presto.tests.TestSpilledAggregations', failingMethods=[com.facebook.presto.tests.TestSpilledAggregations#testGroupByArray], erroringMethods=[], failures=[FailureType{failureName='java.lang.AssertionError', failureDetail='Execution of 'actual' query failed: SELECT col[1], count FROM (SELECT ARRAY[custkey] col, COUNT(*) count FROM orders GROUP BY 1 ORDER BY 1)', isError=false}], nbFailures=1, nbErrors=0}
status: NOPATCH
dateEnd: Wed Mar 21 08:27:18 CET 2018
allocatedtime: 120minutes 
passingTime: 0minutes 
nb patches: 0
nopol context: Config{synthesisDepth=3, collectStaticMethods=true, collectStaticFields=false, collectLiterals=false, onlyOneSynthesisResult=false, sortExpressions=true, maxLineInvocationPerTest=250, timeoutMethodInvocation=2000, dataCollectionTimeoutInSecondForSynthesis=900, addWeight=0.19478, subWeight=0.04554, mulWeight=0.0102, divWeight=0.00613, andWeight=0.10597, orWeight=0.05708, eqWeight=0.22798, nEqWeight=0.0, lessEqWeight=0.0255, lessWeight=0.0947, methodCallWeight=0.1, fieldAccessWeight=0.08099, constantWeight=0.14232, variableWeight=0.05195, mode=REPAIR, type=COND_THEN_PRE, synthesis=DYNAMOTH, oracle=ANGELIC, solver=Z3, solverPath='./z3_for_linux', projectSources=[/root/workspace/prestodb/presto/356202150/presto-tests/src/main/java], projectClasspath='[Ljava.net.URL;@5b7c79da', projectTests=[com.facebook.presto.tests.TestSpilledAggregations], complianceLevel=8, outputFolder=./workspace/prestodb/presto/356202150, json=false}
exception: null
nbStatements: 0
nbAngelicValues: 0
ignoreStatus: NOTHING_TO_IGNORE
----------



nopolinfo #6
location: FailureLocation{className='com.facebook.presto.tests.TestOptimizeMixedDistinctAggregations', failingMethods=[com.facebook.presto.tests.TestOptimizeMixedDistinctAggregations#testGroupByArray], erroringMethods=[], failures=[FailureType{failureName='java.lang.AssertionError', failureDetail='Execution of 'actual' query failed: SELECT col[1], count FROM (SELECT ARRAY[custkey] col, COUNT(*) count FROM orders GROUP BY 1 ORDER BY 1)', isError=false}], nbFailures=1, nbErrors=0}
status: NOPATCH
dateEnd: Wed Mar 21 08:27:22 CET 2018
allocatedtime: 120minutes 
passingTime: 0minutes 
nb patches: 0
nopol context: Config{synthesisDepth=3, collectStaticMethods=true, collectStaticFields=false, collectLiterals=false, onlyOneSynthesisResult=false, sortExpressions=true, maxLineInvocationPerTest=250, timeoutMethodInvocation=2000, dataCollectionTimeoutInSecondForSynthesis=900, addWeight=0.19478, subWeight=0.04554, mulWeight=0.0102, divWeight=0.00613, andWeight=0.10597, orWeight=0.05708, eqWeight=0.22798, nEqWeight=0.0, lessEqWeight=0.0255, lessWeight=0.0947, methodCallWeight=0.1, fieldAccessWeight=0.08099, constantWeight=0.14232, variableWeight=0.05195, mode=REPAIR, type=COND_THEN_PRE, synthesis=DYNAMOTH, oracle=ANGELIC, solver=Z3, solverPath='./z3_for_linux', projectSources=[/root/workspace/prestodb/presto/356202150/presto-tests/src/main/java], projectClasspath='[Ljava.net.URL;@1cdc4c6b', projectTests=[com.facebook.presto.tests.TestOptimizeMixedDistinctAggregations], complianceLevel=8, outputFolder=./workspace/prestodb/presto/356202150, json=false}
exception: null
nbStatements: 0
nbAngelicValues: 0
ignoreStatus: NOTHING_TO_IGNORE
----------



