nopolinfo #0
location: FailureLocation{className='org.pitest.mutationtest.build.intercept.timeout.SimpleInfiniteLoopInterceptorTest', failingMethods=[org.pitest.mutationtest.build.intercept.timeout.SimpleInfiniteLoopInterceptorTest#willFindInfiniteLoopsInForLoopWithConditionalReturn, org.pitest.mutationtest.build.intercept.timeout.SimpleInfiniteLoopInterceptorTest#shouldNotFindInfiniteLoopsInForLoopWithConditionalBreak, org.pitest.mutationtest.build.intercept.timeout.SimpleInfiniteLoopInterceptorTest#shouldMatchRealInfiniteLoopFromJodaTimeMutants, org.pitest.mutationtest.build.intercept.timeout.SimpleInfiniteLoopInterceptorTest#shouldFindInfiniteLoopsInForLoopWithhNoConditional], erroringMethods=[], failures=[FailureType{failureName='skipped', failureDetail='need thought', isError=false}, FailureType{failureName='skipped', failureDetail='skipped', isError=false}, FailureType{failureName='org.junit.ComparisonFailure', failureDetail='[With javac compiler did not match as expected Byte code is 
   L0
    LINENUMBER 183 L0
    ALOAD 1
    INVOKEINTERFACE org/joda/time/ReadablePartial.size ()I
    ISTORE 3
   L1
    LINENUMBER 184 L1
    ICONST_0
    ISTORE 4
   L2
    GOTO L3
   L4
    LINENUMBER 185 L4
    ALOAD 2
    ILOAD 4
    IALOAD
    ISTORE 5
   L5
    LINENUMBER 186 L5
    ALOAD 1
    ILOAD 4
    INVOKEINTERFACE org/joda/time/ReadablePartial.getField (I)Lorg/joda/time/DateTimeField;
    ASTORE 6
   L6
    LINENUMBER 187 L6
    ILOAD 5
    ALOAD 6
    INVOKEVIRTUAL org/joda/time/DateTimeField.getMinimumValue ()I
    IF_ICMPGE L7
   L8
    LINENUMBER 188 L8
    NEW org/joda/time/IllegalFieldValueException
    DUP
   L9
    LINENUMBER 189 L9
    ALOAD 6
    INVOKEVIRTUAL org/joda/time/DateTimeField.getType ()Lorg/joda/time/DateTimeFieldType;
    ILOAD 5
    INVOKESTATIC java/lang/Integer.valueOf (I)Ljava/lang/Integer;
   L10
    LINENUMBER 190 L10
    ALOAD 6
    INVOKEVIRTUAL org/joda/time/DateTimeField.getMinimumValue ()I
    INVOKESTATIC java/lang/Integer.valueOf (I)Ljava/lang/Integer;
    ACONST_NULL
   L11
    LINENUMBER 188 L11
    INVOKESPECIAL org/joda/time/IllegalFieldValueException.<init> (Lorg/joda/time/DateTimeFieldType;Ljava/lang/Number;Ljava/lang/Number;Ljava/lang/Number;)V
    ATHROW
   L7
    LINENUMBER 192 L7
    ILOAD 5
    ALOAD 6
    INVOKEVIRTUAL org/joda/time/DateTimeField.getMaximumValue ()I
    IF_ICMPLE L12
   L13
    LINENUMBER 193 L13
    NEW org/joda/time/IllegalFieldValueException
    DUP
   L14
    LINENUMBER 194 L14
    ALOAD 6
    INVOKEVIRTUAL org/joda/time/DateTimeField.getType ()Lorg/joda/time/DateTimeFieldType;
    ILOAD 5
    INVOKESTATIC java/lang/Integer.valueOf (I)Ljava/lang/Integer;
   L15
    LINENUMBER 195 L15
    ACONST_NULL
    ALOAD 6
    INVOKEVIRTUAL org/joda/time/DateTimeField.getMaximumValue ()I
    INVOKESTATIC java/lang/Integer.valueOf (I)Ljava/lang/Integer;
   L16
    LINENUMBER 193 L16
    INVOKESPECIAL org/joda/time/IllegalFieldValueException.<init> (Lorg/joda/time/DateTimeFieldType;Ljava/lang/Number;Ljava/lang/Number;Ljava/lang/Number;)V
    ATHROW
   L12
    LINENUMBER 184 L12
    NOP
   L3
    ILOAD 4
    ILOAD 3
    IF_ICMPLT L4
   L17
    LINENUMBER 199 L17
    ICONST_0
    ISTORE 4
   L18
    GOTO L19
   L20
    LINENUMBER 200 L20
    ALOAD 2
    ILOAD 4
    IALOAD
    ISTORE 5
   L21
    LINENUMBER 201 L21
    ALOAD 1
    ILOAD 4
    INVOKEINTERFACE org/joda/time/ReadablePartial.getField (I)Lorg/joda/time/DateTimeField;
    ASTORE 6
   L22
    LINENUMBER 202 L22
    ILOAD 5
    ALOAD 6
    ALOAD 1
    ALOAD 2
    INVOKEVIRTUAL org/joda/time/DateTimeField.getMinimumValue (Lorg/joda/time/ReadablePartial;[I)I
    IF_ICMPGE L23
   L24
    LINENUMBER 203 L24
    NEW org/joda/time/IllegalFieldValueException
    DUP
   L25
    LINENUMBER 204 L25
    ALOAD 6
    INVOKEVIRTUAL org/joda/time/DateTimeField.getType ()Lorg/joda/time/DateTimeFieldType;
    ILOAD 5
    INVOKESTATIC java/lang/Integer.valueOf (I)Ljava/lang/Integer;
   L26
    LINENUMBER 205 L26
    ALOAD 6
    ALOAD 1
    ALOAD 2
    INVOKEVIRTUAL org/joda/time/DateTimeField.getMinimumValue (Lorg/joda/time/ReadablePartial;[I)I
    INVOKESTATIC java/lang/Integer.valueOf (I)Ljava/lang/Integer;
    ACONST_NULL
   L27
    LINENUMBER 203 L27
    INVOKESPECIAL org/joda/time/IllegalFieldValueException.<init> (Lorg/joda/time/DateTimeFieldType;Ljava/lang/Number;Ljava/lang/Number;Ljava/lang/Number;)V
    ATHROW
   L23
    LINENUMBER 207 L23
    ILOAD 5
    ALOAD 6
    ALOAD 1
    ALOAD 2
    INVOKEVIRTUAL org/joda/time/DateTimeField.getMaximumValue (Lorg/joda/time/ReadablePartial;[I)I
    IF_ICMPLE L28
   L29
    LINENUMBER 208 L29
    NEW org/joda/time/IllegalFieldValueException
    DUP
   L30
    LINENUMBER 209 L30
    ALOAD 6
    INVOKEVIRTUAL org/joda/time/DateTimeField.getType ()Lorg/joda/time/DateTimeFieldType;
    ILOAD 5
    INVOKESTATIC java/lang/Integer.valueOf (I)Ljava/lang/Integer;
   L31
    LINENUMBER 210 L31
    ACONST_NULL
    ALOAD 6
    ALOAD 1
    ALOAD 2
    INVOKEVIRTUAL org/joda/time/DateTimeField.getMaximumValue (Lorg/joda/time/ReadablePartial;[I)I
    INVOKESTATIC java/lang/Integer.valueOf (I)Ljava/lang/Integer;
   L32
    LINENUMBER 208 L32
    INVOKESPECIAL org/joda/time/IllegalFieldValueException.<init> (Lorg/joda/time/DateTimeFieldType;Ljava/lang/Number;Ljava/lang/Number;Ljava/lang/Number;)V
    ATHROW
   L28
    LINENUMBER 199 L28
    IINC 4 1
   L19
    ILOAD 4
    ILOAD 3
    IF_ICMPLT L20
   L33
    LINENUMBER 213 L33
    RETURN
   L34
    LOCALVARIABLE this Lorg/joda/time/chrono/BaseChronology; L0 L34 0
    LOCALVARIABLE partial Lorg/joda/time/ReadablePartial; L0 L34 1
    LOCALVARIABLE values [I L0 L34 2
    LOCALVARIABLE size I L1 L34 3
    LOCALVARIABLE i I L2 L17 4
    LOCALVARIABLE value I L5 L12 5
    LOCALVARIABLE field Lorg/joda/time/DateTimeField; L6 L12 6
    LOCALVARIABLE i I L18 L33 4
    LOCALVARIABLE value I L21 L28 5
    LOCALVARIABLE field Lorg/joda/time/DateTimeField; L22 L28 6
    MAXSTACK = 8
    MAXLOCALS = 7
] expected:<[tru]e> but was:<[fals]e>', isError=false}, FailureType{failureName='skipped', failureDetail='not implemented yet', isError=false}], nbFailures=4, nbErrors=0}
status: NOPATCH
dateEnd: Wed Jun 28 12:46:03 CEST 2017
allocatedtime: 120minutes 
passingTime: 5minutes 
nb patches: 0
nopol context: Config{synthesisDepth=3, collectStaticMethods=true, collectStaticFields=false, collectLiterals=false, onlyOneSynthesisResult=false, sortExpressions=true, maxLineInvocationPerTest=250, timeoutMethodInvocation=2000, dataCollectionTimeoutInSecondForSynthesis=900, addWeight=0.19478, subWeight=0.04554, mulWeight=0.0102, divWeight=0.00613, andWeight=0.10597, orWeight=0.05708, eqWeight=0.22798, nEqWeight=0.0, lessEqWeight=0.0255, lessWeight=0.0947, methodCallWeight=0.1, fieldAccessWeight=0.08099, constantWeight=0.14232, variableWeight=0.05195, mode=REPAIR, type=COND_THEN_PRE, synthesis=DYNAMOTH, oracle=ANGELIC, solver=Z3, solverPath='./z3_for_linux', projectSources=[/root/workspace/hcoles/pitest/247833128/pitest-entry/src/main/java], projectClasspath='[Ljava.net.URL;@18e7143f', projectTests=[org.pitest.mutationtest.build.intercept.timeout.SimpleInfiniteLoopInterceptorTest], complianceLevel=8, outputFolder=null, json=false}
exception: null
nbStatements: 118
nbAngelicValues: 43
ignoreStatus: NOTHING_TO_IGNORE
----------



